Workbook

Sheet Métricas
A1: jh
B2: 📊 DASHBOARD CRM — OPENCORE
B4: Total Prospectos | C4: Contactadas | D4: No Contactadas | E4: Reuniones Agendadas | F4: Tasa de Conversión
B5: =COUNTA(CUENTAS_VIP_TOP!A:A)-1+COUNTA(INTELIGENCIA_MERCADO!A:A)-1+COUNTA(BASE_COMPLETA_LIMPIA!A:A)-1 | C5: =COUNTIF(CUENTAS_VIP_TOP!N:N, "Contactada")+COUNTIF(INTELIGENCIA_MERCADO!M:M, "Contactada")+COUNTIF(BASE_COMPLETA_LIMPIA!L:L, "Contactada") | D5: =B5-C5 | E5: =COUNTIF(CUENTAS_VIP_TOP!O:O, "Reunión agendada")+COUNTIF(INTELIGENCIA_MERCADO!N:N, "Reunión agendada")+COUNTIF(BASE_COMPLETA_LIMPIA!M:M, "Reunión agendada") | F5: =IF(C5=0, 0, E5/C5)
B7: Resumen por Segmento | C7: VIP Top | D7: Intelig. Mercado | E7: Base Completa | F7: TOTAL
B8: Total Prospectos | C8: =COUNTA(CUENTAS_VIP_TOP!A:A)-1 | D8: =COUNTA(INTELIGENCIA_MERCADO!A:A)-1 | E8: =COUNTA(BASE_COMPLETA_LIMPIA!A:A)-1 | F8: =COUNTA(CUENTAS_VIP_TOP!A:A)-1+COUNTA(INTELIGENCIA_MERCADO!A:A)-1+COUNTA(BASE_COMPLETA_LIMPIA!A:A)-1
B9: Contactadas | C9: =COUNTIF(CUENTAS_VIP_TOP!N:N, "Contactada") | D9: =COUNTIF(INTELIGENCIA_MERCADO!M:M, "Contactada") | E9: =COUNTIF(BASE_COMPLETA_LIMPIA!L:L, "Contactada") | F9: =COUNTIF(CUENTAS_VIP_TOP!N:N, "Contactada")+COUNTIF(INTELIGENCIA_MERCADO!M:M, "Contactada")+COUNTIF(BASE_COMPLETA_LIMPIA!L:L, "Contactada")
B10: No Contactadas | C10: =C8-C9 | D10: =D8-D9 | E10: =E8-E9 | F10: =F8-F9
B12: Estado de Gestión | C12: VIP Top | D12: Intelig. Mercado | E12: Base Completa | F12: TOTAL
B13: Reunión agendada | C13: =COUNTIF(CUENTAS_VIP_TOP!O:O, "Reunión agendada") | D13: =COUNTIF(INTELIGENCIA_MERCADO!N:N, "Reunión agendada") | E13: =COUNTIF(BASE_COMPLETA_LIMPIA!M:M, "Reunión agendada") | F13: =COUNTIF(CUENTAS_VIP_TOP!O:O, "Reunión agendada")+COUNTIF(INTELIGENCIA_MERCADO!N:N, "Reunión agendada")+COUNTIF(BASE_COMPLETA_LIMPIA!M:M, "Reunión agendada")
B14: No Reunión | C14: =COUNTIF(CUENTAS_VIP_TOP!O:O, "No Reunión") | D14: =COUNTIF(INTELIGENCIA_MERCADO!N:N, "No Reunión") | E14: =COUNTIF(BASE_COMPLETA_LIMPIA!M:M, "No Reunión") | F14: =COUNTIF(CUENTAS_VIP_TOP!O:O, "No Reunión")+COUNTIF(INTELIGENCIA_MERCADO!N:N, "No Reunión")+COUNTIF(BASE_COMPLETA_LIMPIA!M:M, "No Reunión")
B15: No le interesó | C15: =COUNTIF(CUENTAS_VIP_TOP!O:O, "No le interesó") | D15: =COUNTIF(INTELIGENCIA_MERCADO!N:N, "No le interesó") | E15: =COUNTIF(BASE_COMPLETA_LIMPIA!M:M, "No le interesó") | F15: =COUNTIF(CUENTAS_VIP_TOP!O:O, "No le interesó")+COUNTIF(INTELIGENCIA_MERCADO!N:N, "No le interesó")+COUNTIF(BASE_COMPLETA_LIMPIA!M:M, "No le interesó")
B16: Lo verá | C16: =COUNTIF(CUENTAS_VIP_TOP!O:O, "Lo verá") | D16: =COUNTIF(INTELIGENCIA_MERCADO!N:N, "Lo verá") | E16: =COUNTIF(BASE_COMPLETA_LIMPIA!M:M, "Lo verá") | F16: =COUNTIF(CUENTAS_VIP_TOP!O:O, "Lo verá")+COUNTIF(INTELIGENCIA_MERCADO!N:N, "Lo verá")+COUNTIF(BASE_COMPLETA_LIMPIA!M:M, "Lo verá")
B17: Me llamará | C17: =COUNTIF(CUENTAS_VIP_TOP!O:O, "Me llamará") | D17: =COUNTIF(INTELIGENCIA_MERCADO!N:N, "Me llamará") | E17: =COUNTIF(BASE_COMPLETA_LIMPIA!M:M, "Me llamará") | F17: =COUNTIF(CUENTAS_VIP_TOP!O:O, "Me llamará")+COUNTIF(INTELIGENCIA_MERCADO!N:N, "Me llamará")+COUNTIF(BASE_COMPLETA_LIMPIA!M:M, "Me llamará")
B18: Otro | C18: =COUNTIF(CUENTAS_VIP_TOP!O:O, "Otro") | D18: =COUNTIF(INTELIGENCIA_MERCADO!N:N, "Otro") | E18: =COUNTIF(BASE_COMPLETA_LIMPIA!M:M, "Otro") | F18: =COUNTIF(CUENTAS_VIP_TOP!O:O, "Otro")+COUNTIF(INTELIGENCIA_MERCADO!N:N, "Otro")+COUNTIF(BASE_COMPLETA_LIMPIA!M:M, "Otro")
B21: Canal de Contacto | C21: VIP Top | D21: Intelig. Mercado | E21: Base Completa | F21: TOTAL
B22: LinkedIn | C22: =COUNTIF(CUENTAS_VIP_TOP!R:R, "LinkedIn") | D22: =COUNTIF(INTELIGENCIA_MERCADO!Q:Q, "LinkedIn") | E22: =COUNTIF(BASE_COMPLETA_LIMPIA!P:P, "LinkedIn") | F22: =COUNTIF(CUENTAS_VIP_TOP!R:R, "LinkedIn")+COUNTIF(INTELIGENCIA_MERCADO!Q:Q, "LinkedIn")+COUNTIF(BASE_COMPLETA_LIMPIA!P:P, "LinkedIn")
B23: Correo | C23: =COUNTIF(CUENTAS_VIP_TOP!R:R, "Correo") | D23: =COUNTIF(INTELIGENCIA_MERCADO!Q:Q, "Correo") | E23: =COUNTIF(BASE_COMPLETA_LIMPIA!P:P, "Correo") | F23: =COUNTIF(CUENTAS_VIP_TOP!R:R, "Correo")+COUNTIF(INTELIGENCIA_MERCADO!Q:Q, "Correo")+COUNTIF(BASE_COMPLETA_LIMPIA!P:P, "Correo")
B24: Teléfono | C24: =COUNTIF(CUENTAS_VIP_TOP!R:R, "Teléfono") | D24: =COUNTIF(INTELIGENCIA_MERCADO!Q:Q, "Teléfono") | E24: =COUNTIF(BASE_COMPLETA_LIMPIA!P:P, "Teléfono") | F24: =COUNTIF(CUENTAS_VIP_TOP!R:R, "Teléfono")+COUNTIF(INTELIGENCIA_MERCADO!Q:Q, "Teléfono")+COUNTIF(BASE_COMPLETA_LIMPIA!P:P, "Teléfono")
B25: Contacto Directo | C25: =COUNTIF(CUENTAS_VIP_TOP!R:R, "Contacto Directo") | D25: =COUNTIF(INTELIGENCIA_MERCADO!Q:Q, "Contacto Directo") | E25: =COUNTIF(BASE_COMPLETA_LIMPIA!P:P, "Contacto Directo") | F25: =COUNTIF(CUENTAS_VIP_TOP!R:R, "Contacto Directo")+COUNTIF(INTELIGENCIA_MERCADO!Q:Q, "Contacto Directo")+COUNTIF(BASE_COMPLETA_LIMPIA!P:P, "Contacto Directo")
B28: Conversión por Canal | C28: Contactados | D28: Reuniones | E28: Tasa de Éxito
B29: LinkedIn | C29: =COUNTIF(CUENTAS_VIP_TOP!R:R, "LinkedIn")+COUNTIF(INTELIGENCIA_MERCADO!Q:Q, "LinkedIn")+COUNTIF(BASE_COMPLETA_LIMPIA!P:P, "LinkedIn") | D29: =COUNTIFS(CUENTAS_VIP_TOP!R:R, "LinkedIn", CUENTAS_VIP_TOP!O:O, "Reunión agendada")+COUNTIFS(INTELIGENCIA_MERCADO!Q:Q, "LinkedIn", INTELIGENCIA_MERCADO!N:N, "Reunión agendada")+COUNTIFS(BASE_COMPLETA_LIMPIA!P:P, "LinkedIn", BASE_COMPLETA_LIMPIA!M:M, "Reunión agendada") | E29: =IF(C29=0, 0, D29/C29)
B30: Correo | C30: =COUNTIF(CUENTAS_VIP_TOP!R:R, "Correo")+COUNTIF(INTELIGENCIA_MERCADO!Q:Q, "Correo")+COUNTIF(BASE_COMPLETA_LIMPIA!P:P, "Correo") | D30: =COUNTIFS(CUENTAS_VIP_TOP!R:R, "Correo", CUENTAS_VIP_TOP!O:O, "Reunión agendada")+COUNTIFS(INTELIGENCIA_MERCADO!Q:Q, "Correo", INTELIGENCIA_MERCADO!N:N, "Reunión agendada")+COUNTIFS(BASE_COMPLETA_LIMPIA!P:P, "Correo", BASE_COMPLETA_LIMPIA!M:M, "Reunión agendada") | E30: =IF(C30=0, 0, D30/C30)
B31: Teléfono | C31: =COUNTIF(CUENTAS_VIP_TOP!R:R, "Teléfono")+COUNTIF(INTELIGENCIA_MERCADO!Q:Q, "Teléfono")+COUNTIF(BASE_COMPLETA_LIMPIA!P:P, "Teléfono") | D31: =COUNTIFS(CUENTAS_VIP_TOP!R:R, "Teléfono", CUENTAS_VIP_TOP!O:O, "Reunión agendada")+COUNTIFS(INTELIGENCIA_MERCADO!Q:Q, "Teléfono", INTELIGENCIA_MERCADO!N:N, "Reunión agendada")+COUNTIFS(BASE_COMPLETA_LIMPIA!P:P, "Teléfono", BASE_COMPLETA_LIMPIA!M:M, "Reunión agendada") | E31: =IF(C31=0, 0, D31/C31)
B32: Contacto Directo | C32: =COUNTIF(CUENTAS_VIP_TOP!R:R, "Contacto Directo")+COUNTIF(INTELIGENCIA_MERCADO!Q:Q, "Contacto Directo")+COUNTIF(BASE_COMPLETA_LIMPIA!P:P, "Contacto Directo") | D32: =COUNTIFS(CUENTAS_VIP_TOP!R:R, "Contacto Directo", CUENTAS_VIP_TOP!O:O, "Reunión agendada")+COUNTIFS(INTELIGENCIA_MERCADO!Q:Q, "Contacto Directo", INTELIGENCIA_MERCADO!N:N, "Reunión agendada")+COUNTIFS(BASE_COMPLETA_LIMPIA!P:P, "Contacto Directo", BASE_COMPLETA_LIMPIA!M:M, "Reunión agendada") | E32: =IF(C32=0, 0, D32/C32)
B35: Pipeline (Embudo) | C35: Cantidad | D35: % del Total
B36: Total Prospectos | C36: =COUNTA(CUENTAS_VIP_TOP!A:A)-1+COUNTA(INTELIGENCIA_MERCADO!A:A)-1+COUNTA(BASE_COMPLETA_LIMPIA!A:A)-1 | D36: =IF(C$36=0, 0, C36/C$36)
B37: Contactadas | C37: =COUNTIF(CUENTAS_VIP_TOP!N:N, "Contactada")+COUNTIF(INTELIGENCIA_MERCADO!M:M, "Contactada")+COUNTIF(BASE_COMPLETA_LIMPIA!L:L, "Contactada") | D37: =IF(C$36=0, 0, C37/C$36)
B38: En Seguimiento | C38: =COUNTIF(CUENTAS_VIP_TOP!O:O, "Lo verá")+COUNTIF(INTELIGENCIA_MERCADO!N:N, "Lo verá")+COUNTIF(BASE_COMPLETA_LIMPIA!M:M, "Lo verá")+COUNTIF(CUENTAS_VIP_TOP!O:O, "Me llamará")+COUNTIF(INTELIGENCIA_MERCADO!N:N, "Me llamará")+COUNTIF(BASE_COMPLETA_LIMPIA!M:M, "Me llamará") | D38: =IF(C$36=0, 0, C38/C$36)
B39: Reuniones Agendadas | C39: =COUNTIF(CUENTAS_VIP_TOP!O:O, "Reunión agendada")+COUNTIF(INTELIGENCIA_MERCADO!N:N, "Reunión agendada")+COUNTIF(BASE_COMPLETA_LIMPIA!M:M, "Reunión agendada") | D39: =IF(C$36=0, 0, C39/C$36)
B42: Seguimientos | C42: Cantidad
B43: ⚠ Vencidos (pasó la fecha) | C43: =COUNTIFS(CUENTAS_VIP_TOP!S:S, "<"&TODAY(), CUENTAS_VIP_TOP!S:S, "<>"&"")+COUNTIFS(INTELIGENCIA_MERCADO!R:R, "<"&TODAY(), INTELIGENCIA_MERCADO!R:R, "<>"&"")+COUNTIFS(BASE_COMPLETA_LIMPIA!Q:Q, "<"&TODAY(), BASE_COMPLETA_LIMPIA!Q:Q, "<>"&"")
B44: 📌 Para Hoy | C44: =COUNTIFS(CUENTAS_VIP_TOP!S:S, "="&TODAY())+COUNTIFS(INTELIGENCIA_MERCADO!R:R, "="&TODAY())+COUNTIFS(BASE_COMPLETA_LIMPIA!Q:Q, "="&TODAY())
B45: 📅 Pendientes (futuro) | C45: =COUNTIFS(CUENTAS_VIP_TOP!S:S, ">"&TODAY())+COUNTIFS(INTELIGENCIA_MERCADO!R:R, ">"&TODAY())+COUNTIFS(BASE_COMPLETA_LIMPIA!Q:Q, ">"&TODAY())

Sheet INTELIGENCIA_MERCADO
A1: Empresa | B1: Rubro | C1: Ciudad | D1: Proyecto / Oportunidad Detectada | E1: Fuente de Información | F1: Enlace a la Fuente | G1: Contacto Sniper | H1: Email de Contacto | I1: LinkedIn | J1: LinkedIn Empresa | K1: Sitio Web | L1: Contexto Empresa | M1: Estado Contacto | N1: Sub-Estado | O1: Fecha Contacto | P1: Notas CRM | Q1: Medio de Contacto | R1: Próximo Seguimiento | S1: Prioridad | T1: RUT | U1: Teléfono | V1: Fecha_Email_Enviado
A2: A. Hartrodt Chile S.A. | B2: Transporte Aéreo, Transporte Marítimo, Transporte Terrestre | C2: Santiago | D2: Investigación en Proceso | G2: Hector Calderon (Jefe Informática) | H2: hcalderon@hartrodt.cl | I2: https://cl.linkedin.com/in/hector-calderon-gonzalez-3439a358 | J2: https://cl.linkedin.com/company/a-hartrodt-chile | L2: Ventas: GRANDE 3 (600.000 - 1.000.000 UF) | Empleados: 34 | M2: Contactada | Q2: LinkedIn | T2: 84.007.300-9 | U2: (56) 2 2483 7000
A3: A.J. Broom y Cía. S.A.C. | B3: Agencias Marítimas | C3: Santiago | D3: Plataforma Tracking Marítimo Real-Time | F3: https://www.ajbroom.cl/ | G3: Ricardo Lira (Gerente Operaciones) | J3: https://cl.linkedin.com/company/broom-group | L3: Ventas: GRANDE 2 (200.000 - 600.000 UF) | Empleados: 33 | M3: Contactada | Q3: LinkedIn | T3: 91.256.000-7 | U3: (56) 2 2549 8400
A4: AB Arriendos S.A. | B4: Arriendo de Equipos para Soldar, Compresores | C4: Santiago | D4: Expansión Arriendo Maquinaria Norte | F4: https://www.abarriendos.cl/ | G4: Roberto Carlos Bailac (Exec. Director) | J4: https://cl.linkedin.com/company/abarriendos | L4: Ventas: GRANDE 2 (200.000 - 600.000 UF) | Empleados: 107 | M4: Contactada | Q4: LinkedIn | T4: 96.872.010-4 | U4: (56) 2 2351 5400
A5: Aceros Chilca | B5: Bolas de Acero Forjado para Molienda, Bolas para molienda, Revestimientos para Molinos | C5: Santiago | D5: Modernización Fundición Piezas Mineras | F5: https://www.aceroschilca.com/ | G5: Eduardo Garcia (Country Manager) | J5: https://cl.linkedin.com/company/aceros-chilca-mepsa | L5: Ventas: GRANDE 2 (200.000 - 600.000 UF) | Empleados: 4 | M5: No Contactada | T5: 96.871.960-2 | U5: (56) 2 2929 5486
A6: Acetogen Gas Chile S.A. | B6: Artículos para Seguridad | C6: Santiago | D6: Investigación en Proceso | G6: Hugo Inzulza Daneri (Gerente General) | H6: hinzulza@acetogen.cl | J6: https://cl.linkedin.com/company/acetogen | L6: Ventas: GRANDE 3 (600.000 - 1.000.000 UF) | Empleados: 57 | M6: Contactada | Q6: LinkedIn | T6: 93.333.000-1 | U6: (56) 2 2583 2780
A7: Adler Steel Chile | B7: Aceros Antiabrasivos, Barras de Aceros Especiales | C7: Santiago | D7: Aceros Especiales Minería (Procesos Críticos) | E7: Portal Minero / Licitaciones | F7: https://adler.cl/wp-content/uploads/2023/06/CatalogoAdlerJunio23.pdf | G7: Sabin Capetillo (Jefe Informática) | H7: scapetillo@adlersteel.cl | I7: https://cl.linkedin.com/in/sabin-capetillo-83376711a | J7: https://cl.linkedin.com/company/adler-steel-chile | L7: Ventas: GRANDE 3 (600.000 - 1.000.000 UF) | Empleados: 17 | M7: Contactada | Q7: LinkedIn | T7: 92.844.000-1 | U7: (56) 2 2420 5555
A8: AeroRescate Ambulancias Aéreas | B8: Transporte Aéreo, Transporte Aéreo en Helicóptero | C8: Santiago | D8: Investigación en Proceso | G8: David Acevedo Olguín (Director Corporativo) | H8: dacevedo@dap.cl | I8: https://cl.linkedin.com/in/david-acevedo-olgu%C3%ADn-01586b56 | J8: https://cl.linkedin.com/company/grupo-dap | L8: Ventas: GRANDE 4 (Mas de 1.000.000 UF) | Empleados: 35 | M8: Contactada | Q8: LinkedIn | T8: 99.543.620-5 | U8: (56) 2 3202 6890
A9: Aerocardal Ltda. | B9: Transporte Aéreo en Helicóptero, Vuelos Ambulancia | C9: Santiago | D9: Mantenimiento Digital Embraer (Servicio Autorizado) | E9: Comunicado Embraer / Newsletter | F9: https://tallyho.cl/embraer-suma-a-aerocardal-a-su-red-de-servicios-autorizados-en-chile/ | G9: Javier Arellano (Jefe IT) | H9: jarellano@aerocardal.com | I9: https://cl.linkedin.com/in/javier-arellano-28087313 | J9: https://cl.linkedin.com/company/aerocardal | L9: Ventas: GRANDE 3 (600.000 - 1.000.000 UF) | Empleados: 98 | M9: Contactada | Q9: LinkedIn | T9: 78.035.640-5 | U9: (56) 2 2377 7400
A10: Aguasin SpA | B10: Sistemas para Purificación de Agua, Tratamiento de Aguas | C10: Santiago | D10: Mantención Telemetría Plantas PW | E10: Mercado Público (ID 4076-121-LE25) | F10: https://www.portalminero.com/noticias/aguasin-y-xylem-presentan-soluciones-digitales-para-el-tratamiento-de-aguas/ | G10: Richard Correa (Gerente Admin (IT Resp)) | H10: rcorrea@aguasin.com | I10: https://cl.linkedin.com/in/richard-correa-escudero-6820b484 | J10: Aguasin | LinkedIn | L10: Ventas: GRANDE 4 (Mas de 1.000.000 UF) | Empleados: 174 | M10: Contactada | Q10: LinkedIn | T10: 76.377.649-2 | U10: (56) 2 2270 9500
A11: Agunsa, Agencias Universales S.A. | B11: Agencias de Carga, Almacenamiento de Carga, Transporte de Minerales | C11: Santiago | D11: Estrategia Global Innovación Digital | E11: LinkedIn | F11: https://cl.linkedin.com/in/carlos-ram%C3%ADrez-c%C3%A1rdenas-8b9b2b2a | G11: Carlos Ramírez (CTO Corporativo) | I11: https://cl.linkedin.com/in/carlos-ram%C3%ADrez-c%C3%A1rdenas-tecnolog%C3%ADa | J11: https://cl.linkedin.com/company/agunsa | L11: Ventas: GRANDE (Estimado por Empleados) | Empleados: 796 | M11: Contactada | Q11: LinkedIn | T11: 96.566.940-K | U11: (56) 2 2460 2700
A12: Alessandri & Cía. Ltda. | B12: Asesorías Jurídicas en Minería, Servicios Legales | C12: Santiago | D12: Implementación LegalTech & Ciberseguridad | F12: https://cl.linkedin.com/in/francisco-fern%C3%A1ndez-mancilla | G12: Francisco Javier Fernández M. (Subgerente Ops) | I12: https://cl.linkedin.com/in/francisco-fern%C3%A1ndez-mancilla | J12: https://cl.linkedin.com/company/alessandri | L12: Ventas: GRANDE 3 (600.000 - 1.000.000 UF) | Empleados: 101 | M12: Contactada | Q12: LinkedIn | T12: 79.784.430-6 | U12: (56) 2 2787 6000
A13: Alfa People Chile SpA | B13: Diseño de Sistemas ERP | C13: Santiago | D13: Proyectos Microsoft Dynamics 365 Cloud | F13: https://alfapeople.com/cl/ | G13: Carlos Amaro (CEO) | J13: https://www.linkedin.com/company/alfapeople | L13: Ventas: GRANDE 3 (600.000 - 1.000.000 UF) | Empleados: 121 | M13: Contactada | Q13: LinkedIn | T13: 76.360.577-9 | U13: (56) 2 2751 9000
A14: Aliservice | B14: Alimentación Industrial | C14: Santiago | D14: Digitalización Cadena Suministro Alimentación | F14: https://www.aliservice.cl/ | G14: Luis Alberto Santana (Gerente Adm y Finanzas) | J14: https://www.linkedin.com/company/aliservice-s-a | L14: Ventas: GRANDE 3 (600.000 - 1.000.000 UF) | Empleados: 1372 | M14: Contactada | Q14: LinkedIn | T14: 76437608-0 | U14: (56) 2 2913 5500
A15: American Parts | B15: Actividades de Apoyo para la Explotación de Minas y Canteras, Venta de Partes, Piezas y Accesorios para Vehículos Automotores | C15: Antofagasta | D15: Canal E-commerce B2B (Expansión Digital) | E15: Americanparts.cl / LinkedIn | F15: https://americanparts.cl/shop/ | G15: Patricio Herrera (Jefe de Sistemas) | H15: p.herrera@americanparts.cl | J15: https://cl.linkedin.com/company/american-parts-spa | K15: http://www.americanparts.cl | L15: Ventas: GRANDE 3 (600.000 - 1.000.000 UF) | Empleados: 38 | T15: 76.790.684-6 | U15: (56) 9 4220 1935
A16: Anakena Group | B16: Construcciones Modulares, Servicios Hoteleros | C16: Santiago | D16: Hotelería Modular Minería (Sistemas Gestión) | E16: Exponor 2024 / BCN | F16: https://www.anakenagroup.cl/2024/06/10/anakena-noticias/ | G16: Michael Salameh (Jefe de Sistemas Producción) | H16: m.salameh@anakena.cl | I16: https://cl.linkedin.com/in/michael-salameh-148509ab | J16: https://www.linkedin.com/company/anakena-chile | L16: Ventas: GRANDE 3 (600.000 - 1.000.000 UF) | Empleados: 476 | T16: 52.003.237-1 | U16: (56) 2 2951 5328
A17: Ancor Tecmin | B17: Aisladores para Anodos y Cátodos, Celdas Electrolíticas | C17: Santiago | D17: Investigación en Proceso | G17: Franco Yáñez (Jefe Automatización e Informática) | H17: f.yanez@ancortecmin.cl | I17: https://cl.linkedin.com/in/francoyanez | J17: https://cl.linkedin.com/company/ancor-tecmin | L17: Ventas: GRANDE 3 (600.000 - 1.000.000 UF) | Empleados: 191 | T17: 76.411.929-0 | U17: (56) 2 2510 6000
A18: Andes Solar | B18: Desarrollo, Construcción y Operación de Proyectos de Energía Renovable | C18: Santiago | D18: Investigación en Proceso | G18: Felipe Aguilera Moore (Jefe de Ingeniería) | H18: f.aguilera@andessolar.cl | I18: https://cl.linkedin.com/in/felipe-aguilera-moore | J18: https://www.linkedin.com/company/andessolar | L18: Ventas: GRANDE 3 (600.000 - 1.000.000 UF) | Empleados: 95 | T18: 76.271.321-7 | U18: (56) 2 2956 6230
A19: Anglo American Chile | B19: Anodos de Cobre, Cátodos de Cobre, Concentrado de Molibdeno, Sulfato de Cobre | C19: Santiago | D19: Centro Remoto IROC | E19: LinkedIn | F19: https://cl.linkedin.com/in/rodrigosubiabre | G19: Rodrigo Subiabre (VP Tech & Innov) | I19: https://cl.linkedin.com/in/rodrigo-subiabre-84130844 | J19: https://www.linkedin.com/company/anglo-american | L19: Ventas: GRANDE (Estimado por Empleados) | Empleados: 837 | T19: 77.905.330-K | U19: (56) 2 2230 6000
A20: Artilec Ltda. | B20: Cámaras IP para Vigilancia, Seguridad Industrial y Minera | C20: Santiago | D20: Investigación en Proceso | G20: Mayron Araya (Soporte Informática) | H20: maraya@artilec.cl | I20: https://cl.linkedin.com/in/mayron-araya-30a828b1 | J20: https://www.linkedin.com/company/artilec-ltda | L20: Ventas: GRANDE 3 (600.000 - 1.000.000 UF) | Empleados: 67 | T20: 79.796.310-0 | U20: (56) 2 2240 7500
A21: AtPac Doka | B21: Andamios | C21: Santiago | D21: Encofrados & Seguridad Construcción | F21: https://www.google.com/search?q=AtPac+Doka+Chile+LinkedIn | G21: Aldo Veas (Technical Manager LATAM) | I21: https://cl.linkedin.com/in/aldo-veas-2850534 | J21: https://www.linkedin.com/company/at-pac | L21: Ventas: GRANDE 2 (200.000 - 600.000 UF) | Empleados: 43 | T21: 77.383.881-K | U21: (56) 9 3394 1026
A22: Atlas Renewable Energy | B22: Plantas de Energía Solar | C22: Santiago | D22: Investigación en Proceso | G22: Francisca Latorre H. (Corporate IT Manager) | H22: flatorre@atlasrenewableenergy.com | I22: https://cl.linkedin.com/in/franciscalatorrel | J22: https://www.linkedin.com/company/atlasrenewableenergy | L22: Ventas: GRANDE 3 (600.000 - 1.000.000 UF) | Empleados: 0 | T22: 76376627-6 | U22: (56) 2 2611 8300
A23: BASF Chile S.A. | B23: Productos Químicos para la Minería | C23: Santiago | D23: Transformación Digital Clusters Región Andes | F23: https://cl.linkedin.com/in/jonathan-rojas-diaz | G23: Jonathan Rojas (Gerente Digitalización) | I23: https://cr.linkedin.com/in/jonathan-rojas-diaz | J23: https://www.linkedin.com/company/basf | L23: Ventas: GRANDE (Estimado por Empleados) | Empleados: 256 | T23: 80.043.600-1 | U23: (56) 2 2640 7000
A24: Bailac | B24: Aros y Llantas para Camiones, Reciclaje de Neumáticos OTR | C24: Santiago | D24: Tecnología Gestión Neumáticos & Economía Circular | F24: https://cl.linkedin.com/in/raimundo-bailac-pereira-b53269104 | G24: Raimundo Bailac (GG) | I24: https://cl.linkedin.com/in/raimundo-bailac-pereira-b53269104 | J24: https://cl.linkedin.com/company/bailac-thor | L24: Ventas: GRANDE 2 (200.000 - 600.000 UF) | Empleados: 95 | T24: 79.722.740-4 | U24: (56) 2 2915 9130
A25: Bailac Capacita | B25: Capacitación en Mantenimiento de Equipos Móviles, Capacitación en Seguridad Operacional, Capacitación en Soldadura (Reparación de Equipos y END) | C25: Santiago | D25: Tecnología Gestión Neumáticos & Economía Circular | F25: https://cl.linkedin.com/in/raimundo-bailac-pereira-b53269104 | G25: Raimundo Bailac (GG) | I25: https://cl.linkedin.com/in/raimundo-bailac-pereira-b53269104 | J25: https://cl.linkedin.com/in/bailac-capacita-26a872180 | L25: Ventas: PEQUEÑA 3 (10.000 - 25.000 UF) | Empleados: 5 | T25: 76.217.882-6 | U25: (56) 9 4284 6607
A26: Bailac Thor Saan Ltda. | B26: Recauchaje de Neumáticos, Servicios de Reparación de Neumáticos Gigantes a la Minería | C26: Iquique | D26: Tecnología Gestión Neumáticos & Economía Circular | F26: https://cl.linkedin.com/in/raimundo-bailac-pereira-b53269104 | G26: Raimundo Bailac (GG) | I26: https://cl.linkedin.com/in/raimundo-bailac-pereira-b53269104 | J26: https://cl.linkedin.com/company/bailacsanltda | L26: Ventas: GRANDE 3 (600.000 - 1.000.000 UF) | Empleados: 156 | T26: 78.080.330-4 | U26: (56) 57 251 8300
A27: Barraca de Fierro San Joaquín SpA | B27: Barracas de Acero, Barracas de Fierros | C27: Santiago | D27: Transformación Digital Ventas & Inventario | F27: https://cl.linkedin.com/in/martin-vera-0b1a1b1b | G27: Martín Vera (CIO/CTO) | I27: https://cl.linkedin.com/in/martin-vera-poblete-1622582a4 | J27: https://cl.linkedin.com/company/barraca-de-fierro-san-joaquin-s-a | L27: Ventas: GRANDE 2 (200.000 - 600.000 UF) | Empleados: 21 | T27: 96.654.030-3 | U27: (56) 2 2551 6867
A28: Bartech | B28: Capturadores de Información, Control de Accesos | C28: Santiago | D28: Investigación en Proceso | G28: Raul Lara (Gerente Comercial y Desarrollo) | H28: raul.lara@bartech.cl | I28: https://cl.linkedin.com/in/raul-lara-c-4626264b | J28: https://cl.linkedin.com/company/bartech-chile | L28: Ventas: GRANDE 3 (600.000 - 1.000.000 UF) | Empleados: 20 | T28: 99.539.070-1 | U28: (56) 2 2923 8600
A29: Bechtel Chile Ltda. | B29: Construcción de Plantas Mineras | C29: Santiago | D29: Sistemas IT Ingeniería Minería & Infraestructura | F29: https://cl.linkedin.com/in/felipe-espinoza-yentzen-377a3b67 | G29: Felipe Espinoza (Infrastructure Lead) | I29: https://cl.linkedin.com/in/felipe-espinoza-yentzen-377a3b67 | J29: https://www.linkedin.com/company/bechtel-corporation | L29: Ventas: GRANDE (Estimado por Empleados) | Empleados: 1820 | T29: 95.207.000-2 | U29: (56) 2 2675 1000
A30: Beiben Truck | B30: Bulldozers, Camiones Carreteros y Fuera de Carretera (OTR) | C30: Santiago | D30: Camiones Autónomos para Minería | F30: https://cl.linkedin.com/in/philipp-kaufmann-beiben-truck-94828180 | G30: Philipp Kaufmann (CEO) | I30: https://cl.linkedin.com/in/philipp-kaufmann-beiben-truck-94828180 | J30: https://www.linkedin.com/company/beiben | L30: Ventas: GRANDE 2 (200.000 - 600.000 UF) | Empleados: 13 | T30: 76.077.627-0 | U30: (56) 2 2797 6200
A31: Bertech | B31: Productos Químicos para la Mantención de Equipos Mineros, Productos Químicos para la Minería, Revestimientos Industriales | C31: Santiago | D31: Transf. Digital Revestimientos Industriales | F31: https://cl.linkedin.com/in/pedro-fernandez-parraguez | G31: Pedro Fernández Parraguez (IT Manager) | I31: https://cl.linkedin.com/in/pedro-fernandez-parraguez | J31: https://cl.linkedin.com/company/bertechgroup | L31: Ventas: GRANDE 2 (200.000 - 600.000 UF) | Empleados: 152 | T31: 76.054.686-0 | U31: (56) 2 2246 3485
A32: Biggi (Chile) S.A. | B32: Cocinas Industriales, Equipos para Preparar Alimentos | C32: Santiago | D32: IoT Equipamiento Cocinas Industriales | F32: https://www.biggi.cl/ | G32: Sergio Biggi (Gerente General) | J32: https://cl.linkedin.com/company/biggi | L32: Ventas: GRANDE 2 (200.000 - 600.000 UF) | Empleados: 6 | T32: 91.462.001-5 | U32: (56) 2 2412 6200
A33: Bimex Ltda. | B33: Equipos Eléctricos | C33: Santiago | D33: Modernización Sistemas LIS Laboratorio | F33: https://www.bimex.cl/ | G33: Alberto Harrison (General Manager) | J33: https://www.linkedin.com/company/bimex-limitada | L33: Ventas: GRANDE 2 (200.000 - 600.000 UF) | Empleados: 9 | T33: 78.836.730-9 | U33: (56) 2 2306 2200
A34: Biofiltro | B34: Plantas de Tratamiento de Aguas Servidas | C34: Santiago | D34: Automatización Tratamiento Riles (Sistema BIDA) | F34: https://cl.linkedin.com/in/ignacio-andr%C3%A9s-jofr%C3%A9-valenzuela-69902289 | G34: Ignacio Jofré Valenzuela (Subgerente Proyectos) | I34: https://cl.linkedin.com/in/ignacio-andr%C3%A9s-jofr%C3%A9-valenzuela-69902289 | J34: https://www.linkedin.com/company/biofiltro | L34: Ventas: GRANDE 2 (200.000 - 600.000 UF) | Empleados: 86 | T34: 76.337.422-K | U34: (56) 2 3224 3648
A35: Biotec Chile S.A. | B35: Detergentes | C35: Santiago | D35: Investigación en Proceso | G35: Fabián Deramond (Gerente TI y Transf. Digital) | H35: f.deramond@biotec.cl | I35: https://cl.linkedin.com/in/fabi%C3%A1n-deramond-44064918 | J35: https://cl.linkedin.com/company/biotec-chile-s-a- | L35: Ventas: GRANDE 3 (600.000 - 1.000.000 UF) | Empleados: 77 | T35: 96.025.000-1 | U35: (56) 2 2963 4500
A36: Bombas de Pozo Ltda. | B36: Proveedor Destacado, Accesorios para Perforación, Asesorías, Bombas para Pozos Profundos, Bombas Sumergibles, Bombas Sumergibles para Pozos Profundos, Cables Sumergibles, Cañerías con Hilo, Coplas y Abrazaderas, Reparación de Equipos Hidráulicos, Servicio Técnico, Tableros Eléctricos, Tuberías Flexibles para Pozos Profundos | C36: Santiago | D36: Investigación en Proceso | G36: Mauricio Illanes (Socio Técnico) | H36: m.illanes@bombasdepozo.cl | K36: http://www.bombasdepozo.cl | L36: Ventas: GRANDE 3 (600.000 - 1.000.000 UF) | Empleados: 36 | T36: 78.176.700-K | U36: (56) 2 2842 0700
A37: Bosch Rexroth Chile | B37: Bulldozers, Cargadoras Retroexcavadoras | C37: Santiago | D37: Monitoreo Predictivo | E37: Catálogo Soluciones | F37: https://www.boschrexroth.com/es/cl/noticias-e-historias/mineria/soluciones-bosch-rexroth-para-mineria/ | G37: Oscar Torres (Jefe Proyectos TI) | H37: oscar.torres@boschrexroth.cl | J37: https://cl.linkedin.com/company/bosch-rexroth-chile-spa | L37: Ventas: GRANDE 4 (Mas de 1.000.000 UF) | Empleados: 79 | T37: 76.365.959-3 | U37: (56) 2 2487 3700
A38: Bottai S.A. | B38: Prefabricados de Concreto y Hormigón, Tubos de Concreto y Hormigón | C38: Santiago | D38: Investigación en Proceso | G38: Rodrigo Gimenez Fernandez (Gerente Comercial) | H38: r.gimenez@bottai.cl | I38: https://cl.linkedin.com/in/rodrigogimenezfernandez | J38: https://cl.linkedin.com/company/bottai-s-a | L38: Ventas: GRANDE 3 (600.000 - 1.000.000 UF) | Empleados: 384 | T38: 80.125.100-5 | U38: (56) 2 2413 1200
A39: Bradken Chile | B39: Revestimientos para Molinos | C39: Santiago | D39: Investigación en Proceso | G39: Juan Carlos Rojas (IT Manager) | H39: j.rojas@bradken.com | J39: https://www.linkedin.com/company/bradkenofficial | L39: Ventas: GRANDE 3 (600.000 - 1.000.000 UF) | Empleados: 28 | T39: 76980920-1
A40: Budge Chile SpA | B40: Transmisiones Mecánicas | C40: Iquique | D40: Modernización Grid & Software Energía | F40: https://www.ge.com/news/reports/ge-chile-100-years | G40: Rodrigo Elizondo (CEO Chile) | I40: https://cl.linkedin.com/in/relizondoj | L40: Ventas: GRANDE 1 (100.000 - 200.000 UF) | Empleados: 3 | T40: 76.869.432-K | U40: (56) 2 2885 4224
A41: CEIM - Centro de Entrenamiento Industrial y Minero | B41: Proveedor Destacado, Capacitación, Capacitación de Personal, Capacitación de Soldadores, Capacitación en Especialidades Mineras, Capacitación en Mantenimiento de Equipos Pesados, Capacitación en Operación de Equipos Mineros, Capacitación en Operación de Grúas, Capacitación en Operación de Plantas Mineras, Capacitación en Seguridad y Psicolaboral, Educación para la Minería | C41: Antofagasta | D41: Digitalización Capacitación Minera | F41: https://www.ceim.cl/ | G41: Milton Flores (Gerente Desarrollo Competencias) | I41: https://cl.linkedin.com/in/milton-flores-pardo | J41: https://cl.linkedin.com/company/ceim | K41: http://www.ceim.cl | L41: Ventas: GRANDE 3 (600.000 - 1.000.000 UF) | Empleados: 184 | T41: 74.191.400-K | U41: (56) 55 245 6001
A42: CEIM Ltda. - Certificaciones y Servicios | B42: Proveedor Destacado, Asesorías en Mecánica, Asesorías en Minería, Asesorías en Procesos Mineros, Asesorías en Proyectos Industriales, Asesorías en Seguridad, Certificación de Competencias Laborales, Certificación de Equipos Mineros, Certificación de Grúas, Certificación de Operadores de Maquinarias y Equipos | C42: Antofagasta | D42: Digitalización Capacitación Minera | F42: https://www.ceim.cl/ | G42: Milton Flores (Gerente Desarrollo Competencias) | I42: https://cl.linkedin.com/in/milton-flores-pardo | J42: https://cl.linkedin.com/company/ceim | K42: http://www.ceim.cl | L42: Ventas: GRANDE 3 (600.000 - 1.000.000 UF) | Empleados: 102 | T42: 76.613.900-0 | U42: (56) 55 245 6000
A43: CGE C | B43: Alumbrado Público y Privado (aéreo y subterráneo), Corrientes Débiles, Empalmes, Redes Aéreas y Subterráneas, Sistemas para Aumento de Potencia, Venta, Arriendo e Instalación de Equipos Eléctricos | C43: Santiago | D43: Digitalización Redes | E43: LinkedIn CDO | F43: https://cl.linkedin.com/in/cristian-ormazabal | G43: Cristian Ormazábal (Chief Digital Officer (CDO)) | H43: cormazabal@cge.cl | I43: https://cl.linkedin.com/in/cristian-ormaz%C3%A1bal | J43: https://www.linkedin.com/company/cge-chile | L43: Ventas: GRANDE 4 (Mas de 1.000.000 UF) | Empleados: 52 | T43: 77.316.204-2 | U43: (56) 2 2280 7400
A44: Canon Chile S.A. | B44: Equipos para Oficina | C44: Santiago | D44: Gestión Documental Cloud | E44: Estrategia Regional 2025 | F44: https://www.canon.cl/blog/fortaleciendo-alianzas-y-estrategias-de-negocios-canon-reunio-sus-canales-regionales-en-su | G44: Aaron Fuentes Calderón (Gerente de TI) | H44: afuentes@canon.cl | I44: https://cl.linkedin.com/in/aaron-fuentes-calder%C3%B3n-5a239a58 | J44: https://www.linkedin.com/company/canon-chile-s-a- | L44: Ventas: GRANDE 4 (Mas de 1.000.000 UF) | Empleados: 138 | T44: 96.716.060-1 | U44: (56) 2 2477 6200
A45: Caxtor | B45: Energía Solar | C45: Santiago | D45: Modernización Infraestructura Telecom & Marítima | F45: https://cl.linkedin.com/company/grupo-caxtor | G45: Brian Smith Hanne (Gte Comercial) | I45: https://cl.linkedin.com/in/brian-smith-hanne-901a5a3b | J45: https://www.linkedin.com/company/caxtor | L45: Ventas: GRANDE 2 (200.000 - 600.000 UF) | Empleados: 36 | T45: 76.152.409-7 | U45: (56) 2 2791 9662
A46: Centro Médico del Trabajador (CMT) | B46: Proveedor Destacado, Centro Médico de Salud Ocupacional, Centros Médicos, Reclutamiento y Selección | C46: Santiago | D46: Transformación Digital Salud Ocupacional | F46: https://cl.linkedin.com/in/ignacio-henderson-gonzalez-08108754 | G46: Ignacio Henderson Gonzalez (Director Innovación) | I46: https://cl.linkedin.com/in/ignacio-henderson-gonzalez-08108754 | J46: https://cl.linkedin.com/company/centro-medico-del-trabajador-cmt- | K46: http://www.cmtsalud.cl | L46: Ventas: GRANDE 3 (600.000 - 1.000.000 UF) | Empleados: 388 | T46: 76.247.147-7 | U46: (56) 2 2634 2492
A47: Codelco Chile División Minera Gabriela Mistral | B47: Cobre | C47: Calama | D47: Digitalización Faenas | E47: Reporte Integrado 2024 | F47: https://www.codelco.com/sustentabilidad/reporte-integrado | G47: José Ramón Abatte (Gerente Corp Tecnología) | H47: jabatte@codelco.cl | I47: https://cl.linkedin.com/in/jose-ramon-abatte-14853839 | J47: https://www.linkedin.com/company/codelco | L47: Ventas: No en base SII | Empleados: S/I | T47: 76.685.790-6 | U47: (56) 55 232 8277
A48: Codelco Chile División Salvador | B48: Barro Anódico, Cátodos de Cobre, Cobre, Concentrado de Cobre, Plata | C48: El Salvador | D48: Digitalización Faenas | E48: Reporte Integrado 2024 | F48: https://www.codelco.com/sustentabilidad/reporte-integrado | G48: José Ramón Abatte (Gerente Corp Tecnología) | H48: jabatte@codelco.cl | I48: https://cl.linkedin.com/in/jose-ramon-abatte-14853839 | J48: https://www.linkedin.com/company/codelco | L48: Ventas: GRANDE (Estimado por Empleados) | Empleados: 16946 | T48: 61.704.000-K | U48: (56) 52 247 2514
A49: CodelcoTech | B49: Asesorías en Ingeniería, Asesorías en Procesos Mineros | C49: Santiago | D49: Digitalización Faenas | E49: Reporte Integrado 2024 | F49: https://www.codelco.com/sustentabilidad/reporte-integrado | G49: José Ramón Abatte (Gerente Corp Tecnología) | H49: jabatte@codelco.cl | I49: https://cl.linkedin.com/in/jose-ramon-abatte-14853839 | J49: https://www.linkedin.com/company/codelco | L49: Ventas: MICRO 1 (0.01 - 200 UF) | Empleados: 0 | T49: 96.991.180-9 | U49: (56) 2 2690 3888
A50: Comaco Servicios Logísticos SpA | B50: Arriendo de Grúas, Arriendo de Grúas Horquilla | C50: Santiago | D50: Continuidad Operativa Plantas | E50: LinkedIn | F50: https://cl.linkedin.com/in/ariel-viveros-s%C3%A1ez-a2883650 | G50: Ariel Viveros Sáez (Jefe Proyectos TI) | I50: https://cl.linkedin.com/in/ariel-viveros-s%C3%A1ez-a2883650 | J50: https://cl.linkedin.com/company/comaco-servicios-log-sticos | L50: Ventas: GRANDE 2 (200.000 - 600.000 UF) | Empleados: 61 | T50: 99.587.850-K | U50: (56) 2 2222 3192
A51: Comgrap Ltda. / 3D - BIM | B51: Software para Control de Proyectos, Software para la Minería, Software para Mantenimiento de Plantas Mineras | C51: Santiago | D51: DigitalHub LMS & Estándares BIM ISO 19650 | E51: Comgrap.cl | G51: Ricardo Rizzi Limone (Gerente General) | H51: rrizzi@comgrap.cl | I51: https://cl.linkedin.com/in/ricardo-rizzi-limone-8b456b31 | J51: https://www.linkedin.com/company/comgrap | L51: Ventas: GRANDE 3 (600.000 - 1.000.000 UF) | Empleados: 37 | T51: 79.770.640-K | U51: (56) 2 2592 9000
A52: Constructora Inarco S.A. | B52: Construcción de Obras Civiles, Construcción Industrial | C52: Santiago | D52: Digitalización BIM & Workflows CMS | F52: https://cl.linkedin.com/in/hugo-mu%C3%B1oz-b587061a | G52: Hugo Muñoz (SubGerente TI) | I52: https://cl.linkedin.com/in/mu%C3%B1oz-hugo-02ab903b | J52: https://cl.linkedin.com/company/inarco-constructora | L52: Ventas: GRANDE (Estimado por Empleados) | Empleados: 1654 | T52: 96.513.310-0 | U52: (56) 2 2240 8400
A53: Datamine | B53: Consultoría en Minería, Software | C53: Santiago | D53: Transf. Digital & Software Eficiencia Minera | F53: https://cl.linkedin.com/in/elio-cespedes-b-61763331 | G53: Elio Cespedes B (Gerente General Hispanoamerica) | I53: https://cl.linkedin.com/in/elio-cespedes-b-61763331 | J53: https://cl.linkedin.com/company/datamine | L53: Ventas: GRANDE 2 (200.000 - 600.000 UF) | Empleados: 72 | T53: 96.783.640-0 | U53: (56) 2 2963 9920
A54: Dyno Nobel Explosivos Chile | B54: Proveedor Destacado, Administración de Polvorines, Asistencia Técnica de Tronadura, Asistencia Técnica Geomecánica, Servicios de Tronadura | C54: Santiago | D54: Cibersegurida Industrial | E54: LinkedIn CIO | G54: Julio Solari (CIO & CISO) | H54: julio.solari@am.dynonobel.com | I54: https://cl.linkedin.com/in/julio-solari-40571b13 | J54: https://cl.linkedin.com/company/dynonobel | K54: http://www.dynonobel.lat | L54: Ventas: GRANDE 4 (Mas de 1.000.000 UF) | Empleados: 158 | T54: 76.040.923-5 | U54: (56) 9 3924 1455
A55: ELB - Transportes Libertador | B55: Proveedor Destacado, Transporte de Carga por Carretera, Transporte de Carga Sobredimensionada, Transporte de Cargas Especiales, Transporte de Maquinaria, Transporte de NFU, Transporte en Faena (Home Delivery), Transporte para la Minería | C55: Santiago | D55: Investigación en Proceso | G55: Miguel Angel Vergara (Jefe de Sistemas) | H55: mvergara@elb.cl | I55: https://cl.linkedin.com/in/miguel-angel-alvarez-vergara-81b750b6 | J55: https://cl.linkedin.com/company/transportes-nacionales-libertador-filial-sitrans-grupo-ultramar | K55: http://www.elb.cl | L55: Ventas: GRANDE 3 (600.000 - 1.000.000 UF) | Empleados: 212 | T55: 79.554.850-5 | U55: (56) 9 9344 0371
A56: EPM Chile S.A. | B56: Proyectos para Infraestructura | C56: Santiago | D56: Investigación en Proceso | G56: Fernando Meza (Gerente General (Tech Decision Maker)) | H56: fmeza@epmchile.cl | J56: https://cl.linkedin.com/company/epm-chile-s-a- | L56: Ventas: GRANDE 3 (600.000 - 1.000.000 UF) | Empleados: 3 | T56: 76.266.933-1 | U56: (56) 2 2953 6631
A57: Eaton Chile | B57: Salas Eléctricas, Tableros Eléctricos | C57: Santiago | D57: Fabricación Electrónica para Proyectos EPC | F57: https://cl.linkedin.com/in/miguel-gonzalez-moraga-b3a91962 | G57: Miguel Gonzalez Moraga (Project Manager) | I57: https://cl.linkedin.com/in/miguel-gonzalez-moraga-b3a91962 | J57: https://www.linkedin.com/company/eaton | L57: Ventas: GRANDE (Estimado por Empleados) | Empleados: 437 | T57: 76.103.571-1 | U57: (56) 2 2640 8165
A58: Ecopreneur Chile S.A. | B58: Contratos Llave en Mano | C58: Santiago | D58: Investigación en Proceso | G58: Claudio Fredes (Jefe de Tecnologías) | H58: cfredes@ecopreneur.cl | I58: https://cl.linkedin.com/in/claudiofredes/es | J58: https://es.linkedin.com/company/ecopreneur | L58: Ventas: GRANDE 3 (600.000 - 1.000.000 UF) | Empleados: 44 | T58: 96.778.160-6 | U58: (56) 2 2334 6422
A59: Electroram Telecomunicaciones Ltda. | B59: Radiocomunicaciones, Telecomunicaciones | C59: Antofagasta | D59: Conectividad Satelital Fleet Space Minería | F59: https://cl.linkedin.com/in/martha-aguilera-alderete-850117121 | G59: Martha Aguilera (Gerente Innovación) | I59: https://cl.linkedin.com/in/martha-aguilera-alderete-850117121 | J59: https://cl.linkedin.com/company/electroram-telecomunicaciones | L59: Ventas: GRANDE 2 (200.000 - 600.000 UF) | Empleados: 102 | T59: 76025110-0 | U59: (56) 55 256 1670
A60: Elfle Comercial Dos Ltda. | B60: Artículos Eléctricos, Suministros para Computación | C60: Santiago | D60: Investigación en Proceso | G60: Gabriel Andres Pérez Gonzalez (Encargado TI) | H60: gabriel.perez@elfle.cl | I60: https://cl.linkedin.com/in/gabriel-andres-perez-gonzalez-b72648129 | J60: https://cl.linkedin.com/company/elfle-materiales-el%C3%A9ctricos | L60: Ventas: GRANDE 3 (600.000 - 1.000.000 UF) | Empleados: 24 | T60: 76.085.400-K | U60: (56) 2 2733 3000
A61: Empresas Perrot | B61: Transporte Terrestre | C61: Santiago | D61: Investigación en Proceso | G61: Mario Ceron (Gerente TI & Digital) | H61: mario.ceron@perrot.cl | I61: https://cl.linkedin.com/in/marioceronmorales/es | J61: https://www.linkedin.com/company/empresas-perrot | L61: Ventas: GRANDE 3 (600.000 - 1.000.000 UF) | Empleados: 146 | T61: 77.532.910-6 | U61: (56) 2 2876 2700
A62: Enaex Servicios | B62: Servicios para Tronaduras | C62: Santiago | D62: Transf. Digital OCC & Soluciones IT/OT | F62: https://cl.linkedin.com/in/jcastrogorostiza | G62: Jose Miguel Castro Gorostiza (Gerente Tecnologia) | I62: https://cl.linkedin.com/in/jcastrogorostiza | J62: https://www.linkedin.com/company/enaex | L62: Ventas: GRANDE (Estimado por Empleados) | Empleados: 2168 | T62: 76.041.871-4 | U62: (56) 2 2837 7600
A63: Enapac | B63: Proyecto Planta Desaladora | C63: Santiago | D63: Transformación Digital Energía | E63: LinkedIn | F63: https://cl.linkedin.com/in/jorgejaque | G63: Jorge Jaque (Gerente TI) | I63: https://cl.linkedin.com/in/jorge-jaque-gerente-ti | J63: https://cl.linkedin.com/company/enapac | L63: Ventas: No en base SII | Empleados: S/I | U63: (56) 2 2206 4491
A64: Energías Industriales S.A. (EISA) | B64: Arriendo de Calderas Generadoras a Vapor y Agua Caliente, Asesoría Eficiencia Calderas y Equipos Relacionados, Reparación de Calderas | C64: Santiago | D64: Investigación en Proceso | G64: Mario Tapia Sottorff (Gerente de Operaciones) | H64: mtapia@eisa.cl | I64: https://cl.linkedin.com/in/mario-tapia-sottorff | J64: https://cl.linkedin.com/company/eisa-energias-industriales-sa | L64: Ventas: GRANDE 3 (600.000 - 1.000.000 UF) | Empleados: 198 | T64: 85.145.500-0 | U64: (56) 2 2440 8300
A65: Engineering Composites SpA | B65: Revestimientos de FRP | C65: Santiago | D65: Investigación en Proceso | G65: Alfredo Jose Gonzalez (Jefe de Operaciones TI) | H65: alfredo.gonzalez@engineering.cl | I65: https://cl.linkedin.com/in/alfredo-jose-gonzalez-gonzalez-5aa14235 | J65: https://cl.linkedin.com/company/engineering-composites-spa | L65: Ventas: GRANDE 3 (600.000 - 1.000.000 UF) | Empleados: 460 | T65: 76479832-5
A66: Esri Chile S.A. | B66: Productos Percepción Remota (RS), Sistemas de Información Geográfica (GIS), Sistemas GPS/GNSS Geodésicos y Cartográficos | C66: Santiago | D66: Investigación en Proceso | G66: Ignacio Vergara López (IT Leader) | H66: ivergara@esri.cl | I66: https://cl.linkedin.com/in/ignacio-vergara-lopez-50a109199 | J66: https://cl.linkedin.com/company/esri-chile | L66: Ventas: GRANDE 3 (600.000 - 1.000.000 UF) | Empleados: 106 | T66: 76.504.980-6 | U66: (56) 2 2481 9000
A67: Euro Rent a Car | B67: Arriendo de Camionetas | C67: Santiago | D67: Transf. Digital Gestión Flota | F67: https://www.google.com/search?q=Euro+Rent+a+Car+Chile+Gerente+IT+LinkedIn | G67: Christian Meza (Sub-Gerente TI) | I67: https://cl.linkedin.com/in/christian-meza-b7518292 | J67: https://www.linkedin.com/company/euro-rent-a-car-chile | L67: Ventas: GRANDE 2 (200.000 - 600.000 UF) | Empleados: 77 | T67: 99.501.690-7 | U67: (56) 2 2478 9000
A68: Faiveley Transport Chile (Wabtec Corporation) | B68: Componentes y Servicios para Trenes de Pasajeros, Soluciones Digitales Mercado Ferroviario | C68: Santiago | D68: Infraestructura Ferroviaria Metro & EFE | F68: https://cl.linkedin.com/in/sergio-brito-p | G68: Sergio Brito (Country Manager) | I68: https://cl.linkedin.com/in/sergio-brito-p | J68: https://www.linkedin.com/company/faiveley-transport-chile | L68: Ventas: GRANDE 2 (200.000 - 600.000 UF) | Empleados: 8 | T68: 76.153.216-2 | U68: (56) 2 2426 8558
A69: Fenner Dunlop Chile S.A. | B69: Proveedor Destacado, Correas Transportadoras de Tela y Cables de Acero, Equipos de Monitoreo, Raspadores para Correas Transportadoras, Rayos X y Scanners | C69: Antofagasta | D69: Investigación en Proceso | G69: Manuel García (IT Engineer) | H69: manuel.garcia@fennerdunlop.com | I69: https://cl.linkedin.com/in/miguel-garcia-63b554134 | J69: https://www.linkedin.com/company/fenner-dunlop | K69: http://www.fennerdunlopamericas.com | L69: Ventas: GRANDE 3 (600.000 - 1.000.000 UF) | Empleados: 26 | T69: 76.450.610-3 | U69: (56) 55 249 2314
A70: Ferrocentro - Maestranza Maipú | B70: Servicios en Productos de Acero | C70: Santiago | D70: Investigación en Proceso | G70: Gerente General (Gerente General) | H70: sistemas@ferrocentro.cl | I70: https://cl.linkedin.com/in/luis-m%C3%A1rquez-026a1659 | J70: https://www.linkedin.com/company/industrial-y-comercial-ferrocentro-ltda | L70: Ventas: GRANDE 3 (600.000 - 1.000.000 UF) | Empleados: 161 | T70: 79.677.100-3 | U70: (56) 2 2836 4900
A71: Fertec | B71: Proveedor Destacado, Abrasivos, Corte y Mecanizado, Equipos de Levante, Equipos de Medición y Precisión, Equipos Hidráulicos | C71: Santiago | D71: Investigación en Proceso | G71: Camilo Román Celis (Soporte TI) | H71: c.roman@fertec.cl | I71: https://cl.linkedin.com/in/camilo-rom%C3%A1n-celis-955b2081 | J71: https://cl.linkedin.com/company/fertec-s-a | K71: http://www.fertec.cl | L71: Ventas: GRANDE 3 (600.000 - 1.000.000 UF) | Empleados: 63 | T71: 99.552.660-3 | U71: (56) 55 247 6985
A72: Festo S.A. | B72: Automatización Industrial, Robots industriales | C72: Santiago | D72: Investigación en Proceso | G72: Mauricio Tapia (Regional Head of IT) | H72: m.tapia@festo.com | J72: https://es.linkedin.com/company/festo-chile | L72: Ventas: GRANDE 3 (600.000 - 1.000.000 UF) | Empleados: 42 | T72: 96.951.450-8 | U72: (56) 2 2690 2800
A73: FitFlow | B73: Equipos contra Incendios, Sistemas contra Incendios | C73: Santiago | D73: Investigación en Proceso | G73: Bruno Turrarol (Gerente de Operaciones (IT Resp)) | H73: b.turrarol@fitflow.com | I73: https://pe.linkedin.com/in/brunoturrarol | J73: https://cl.linkedin.com/company/fitflow | L73: Ventas: GRANDE 3 (600.000 - 1.000.000 UF) | Empleados: 158 | T73: 76.652.750-7 | U73: (56) 2 2706 6920
A74: Flender SpA | B74: Acoplamientos, Reductores | C74: Santiago | D74: Digitalización Accionamientos AI-IQ | F74: https://www.flender.com/en/service/digital-services | G74: Javier Iglesias (Gerente Centro Servicios) | I74: https://cl.linkedin.com/in/javier-iglesias-23599543 | J74: https://www.linkedin.com/company/flender | L74: Ventas: GRANDE 3 (600.000 - 1.000.000 UF) | Empleados: 25 | T74: 76879562-2 | U74: (56) 9 8808 3824
A75: Flexco de Chile SpA | B75: Alineadores para Correas Transportadoras | C75: Santiago | D75: IoT en Cintas Transportadoras Inteligentes | F75: https://www.flexco.com/ES/ES/Flexco.htm | G75: Franklin Mendoza (Gerente Operaciones) | I75: https://cl.linkedin.com/in/franklin-jos%C3%A9-mendoza-rosario-7b667575 | J75: https://cl.linkedin.com/company/flexcolatinamerica | L75: Ventas: GRANDE 3 (600.000 - 1.000.000 UF) | Empleados: 42 | T75: 76.126.089-8 | U75: (56) 2 2896 7870
A76: Fourthane | B76: Reparación de Correas Transportadoras | C76: Santiago | D76: Soluciones Tecnológicas Reparación Cintas | F76: http://www.fourthane.com/ | G76: Gerente de Innovación (Gerente Innovación) | I76: https://cl.linkedin.com/in/maria-ignacia-fourt-pimentel | J76: https://cl.linkedin.com/company/fourthane | L76: Ventas: GRANDE 3 (600.000 - 1.000.000 UF) | Empleados: 551 | T76: 76.526.130-9 | U76: (56) 2 2443 6031
A77: Freeport-Mcmoran South America | B77: Concentrados de Cobre | C77: Santiago | D77: Inversión Continuidad El Abra | E77: LinkedIn | F77: https://cl.linkedin.com/in/mariolarenas | G77: Mario Larenas (Country Manager) | I77: https://cl.linkedin.com/in/mariolarenasgonzalez | J77: https://www.linkedin.com/company/freeport-mcmoran | L77: Ventas: GRANDE 4 (Mas de 1.000.000 UF) | Empleados: 72 | T77: 78.273.180-7 | U77: (56) 2 2873 1200
A78: Fundación Ceduc - UCN (Centro de Educación y Capacitación de la U. Católica del Norte) | B78: Capacitación en Especialidades Mineras, Certificación de Operadores de Maquinarias y Equipos | C78: Coquimbo | D78: Investigación en Proceso | G78: Claudio Fredes F. (Jefe TI) | H78: cfredes@ceduc.cl | I78: https://cl.linkedin.com/in/claudio-fredes-f-7492456a | J78: https://www.linkedin.com/company/ceduc-ucn | L78: Ventas: GRANDE 3 (600.000 - 1.000.000 UF) | Empleados: 603 | T78: 74.822.900-0 | U78: (56) 51 254 7000
A79: Fundación Chile | B79: Asesorías en Medioambiente, Capacitación de Personal | C79: Santiago | D79: Hub Metropolitano & Escalado Startups Científico-Tecnológicas | E79: Fch.cl / Talento Digital | G79: Iván Córdova Concha (Subgerente Tecnología) | H79: ivan.cordova@fch.cl | I79: https://cl.linkedin.com/in/ivancordova76 | J79: https://cl.linkedin.com/company/fundaci-n-chile | L79: Ventas: GRANDE 3 (600.000 - 1.000.000 UF) | Empleados: 203 | T79: 70.300.000-2 | U79: (56) 2 2240 0300
A80: Fundición Chagres - Anglo American Sur | B80: Anodos de Cobre, Concentrado de Cobre | C80: Valparaíso | D80: Centro Remoto IROC | E80: LinkedIn | F80: https://cl.linkedin.com/in/rodrigosubiabre | G80: Rodrigo Subiabre (VP Tech & Innov) | I80: https://cl.linkedin.com/in/rodrigo-subiabre-84130844 | J80: https://cl.linkedin.com/company/anglo-american | L80: Ventas: GRANDE (Estimado por Empleados) | Empleados: 2517 | T80: 77.762.940-9 | U80: (56) 2 2230 8600
A81: GE Mining | B81: Equipos para Minería de Superficie, Equipos para Minería Subterránea | C81: Santiago | D81: Investigación en Proceso | G81: Franco Francino (Digital Mining) | H81: franco.francino@ge.com | I81: https://cl.linkedin.com/in/franco-francino-65b32810 | J81: https://www.linkedin.com/company/ge | L81: Ventas: GRANDE 3 (600.000 - 1.000.000 UF) | Empleados: 18 | T81: 59.010.820-0 | U81: (56) 2 2652 6500
A82: GEA Chile | B82: Tratamiento de Efluentes | C82: Santiago | D82: Investigación en Proceso | G82: Francisco Miño Kraus (Soluciones Digitales) | H82: francisco.mino@gea.com | I82: https://cl.linkedin.com/in/francisco-mi%C3%B1o-kraus-21782715 | J82: https://cl.linkedin.com/company/geachile | L82: Ventas: GRANDE 3 (600.000 - 1.000.000 UF) | Empleados: 27 | T82: 96.573.980-7 | U82: (56) 2 3210 9302
A83: GL Group | B83: Circuitos Cerrados de Televisión (CCTV) | C83: Santiago | D83: Tecnología RFID & Transf. Digital Retail | F83: https://cl.linkedin.com/company/glgroup-s-a | G83: Luis Caravello (Gerente Operaciones) | I83: https://cl.linkedin.com/in/luis-caravello-98417366 | J83: https://es.linkedin.com/company/glgroup-s-a | L83: Ventas: GRANDE 2 (200.000 - 600.000 UF) | Empleados: 68 | T83: 77.375.090-4 | U83: (56) 2 2629 2222
A84: GPS Chile SpA | B84: Dispositivos para Control de Conducción de Vehículos, Plataformas GPS para Control y Gestión | C84: Santiago | D84: Investigación en Proceso | G84: Tomás Gantes (Gte Innovación y Producto) | H84: tgantes@gpschile.com | I84: https://cl.linkedin.com/in/tomas-gantes | J84: https://cl.linkedin.com/company/gpschile | L84: Ventas: GRANDE 3 (600.000 - 1.000.000 UF) | Empleados: 152 | T84: 96.941.960-2 | U84: (56) 2 2940 4911
A85: Gasco | B85: Proveedor Destacado, Energía Eléctrica Distribuida, Energía para Calefacción Industrial, Energía para Hornos de Tratamiento Térmico, Energía para Hornos Rotatorios, Energía para Procesos Metalúrgicos y de Metalmecánica | C85: Santiago | D85: Optimización SAP & Transf. Digital CX | F85: https://cl.linkedin.com/in/gsalazarp/ | G85: Guillermo Salazar (Gte Corp Tecnología) | I85: https://cl.linkedin.com/in/guillermo-salazar-pe%C3%B1a-78096333 | J85: https://cl.linkedin.com/company/empresas-gasco | K85: http://solucionesenergeticas.gasco.cl | L85: Ventas: GRANDE (Estimado por Empleados) | Empleados: 1059 | T85: 96.568.740-8 | U85: 600 822 2222
A86: Gauss Control | B86: Software para predecir Indices de Riesgo de los Trabajadores | C86: Santiago | D86: Fatiga & IA Seguridad Operacional | F86: https://www.gausscontrol.com/ | G86: José Rafael Campino (Founder/CEO) | I86: https://cl.linkedin.com/in/jos%C3%A9-rafael-campino-444a2239 | J86: https://cl.linkedin.com/company/gauss-control | L86: Ventas: No en base SII | Empleados: S/I | T86: 96.871.070-2 | U86: (56) 9 6103 7267
A87: Geo Operaciones Ltda. | B87: Servicios para la Minería, Sondajes | C87: Copiapó | D87: Investigación en Proceso | G87: Ricardo Soto (Jefe de Informática) | H87: r.soto@geo-operaciones.cl | J87: https://www.linkedin.com/company/geo-operaciones-ltda. | L87: Ventas: GRANDE 3 (600.000 - 1.000.000 UF) | Empleados: 315 | T87: 79.634.910-7 | U87: (56) 52 220 2900
A88: Geobarra Exins S.A. | B88: Tratamiento de Residuos | C88: Rancagua | D88: Investigación en Proceso | G88: Emilio Briceño (Gerente de Operaciones) | H88: e.briceno@geobarra.cl | I88: https://cl.linkedin.com/in/emilio-hern%C3%A1n-brice%C3%B1o-henr%C3%ADquez-2666a8292 | J88: https://cl.linkedin.com/company/geobarra | L88: Ventas: GRANDE 3 (600.000 - 1.000.000 UF) | Empleados: 311 | T88: 76.562.260-3 | U88: (56) 72 252 2143
A89: Gestión Ambiental Consultores S.A. | B89: Asesorías en Medioambiente | C89: Santiago | D89: Investigación en Proceso | G89: Daniel Maturana (Jefe de TI) | H89: daturana@gac.cl | J89: https://cl.linkedin.com/company/gestionambientalconsultores | L89: Ventas: GRANDE 3 (600.000 - 1.000.000 UF) | Empleados: 314 | T89: 78.174.910-9 | U89: (56) 2 2719 5600
A90: Glencore Chile | B90: Acido Sulfúrico, Anodos de Cobre, Cátodos de Cobre | C90: Santiago | D90: Digitalización Operacional Mina | E90: LinkedIn | F90: https://cl.linkedin.com/in/javier-zamudio-2334ba2 | G90: Javier Zamudio (Regional IT Leader) | I90: https://cl.linkedin.com/in/javier-zamudio-2334ba2 | J90: https://cl.linkedin.com/company/glencore | L90: Ventas: PEQUEÑA (Estimado por Empleados) | Empleados: 50 | T90: 76.821.240-6 | U90: (56) 2 2342 9000
A91: Grafton Recruitment | B91: Selección y Búsqueda de Personal | C91: Santiago | D91: Investigación en Proceso | G91: Marcelo Muñoz (Analista TI) | H91: marcelo.munoz@grafton.cl | J91: https://cl.linkedin.com/company/grupograftonlatam | L91: Ventas: GRANDE 3 (600.000 - 1.000.000 UF) | Empleados: 457 | T91: 96.816.540-2 | U91: (56) 2 2327 3000
A92: Grandleasing | B92: Equipos de Izaje, Vehículos Eléctricos | C92: Santiago | D92: Estrategia Electromovilidad & Monitoreo Telemático de Flotas | E92: LinkedIn / Jedimar | F92: https://www.revistalogistec.com/index.php/2025/02/19/entregan-flota-de-camionetas-electricas-4x4-por-primera-vez-en-chile/ | G92: Marco Rojas (Jefe de TI) | H92: mrojas@grandleasing.cl | I92: https://cl.linkedin.com/in/marco-rojas-8814601aa | J92: https://cl.linkedin.com/company/sociedad-comercial-grandleasing-chile-limitada | L92: Ventas: GRANDE 4 (Mas de 1.000.000 UF) | Empleados: 159 | T92: 76976580-8 | U92: (56) 9 8239 3092
A93: Grupo Avanza | B93: Selección de Personal | C93: Santiago | D93: Investigación en Proceso | G93: Carlos Recabarren (Gerente Avanza Tech) | H93: carlos.recabarren@grupoavanza.cl | I93: https://cl.linkedin.com/in/carlos-recabarren-46487627 | J93: https://www.linkedin.com/company/avanza-think | L93: Ventas: GRANDE 3 (600.000 - 1.000.000 UF) | Empleados: 309 | T93: 76008458-1 | U93: (56) 2 2240 3963
A94: Grupo Eulen Chile | B94: Servicios de Limpieza y Aseo Industrial, Servicios de Seguridad y Vigilancia | C94: Santiago | D94: Ciberseguridad & IA Seguridad Inteligente | F94: https://cl.linkedin.com/in/pablo-ignacio-flores-7aa484106 | G94: Pablo Ignacio Flores (Gerente Op. Seg. Electrónica) | I94: https://cl.linkedin.com/in/pablo-ignacio-flores-7aa484106 | J94: https://cl.linkedin.com/company/grupo-eulen-chile | L94: Ventas: GRANDE 2 (200.000 - 600.000 UF) | Empleados: 169 | T94: 96.997.370-7 | U94: (56) 2 2685 9500
A95: Grúas y Equipos Cruz del Sur | B95: Arriendo de Grúas | C95: Santiago | D95: Investigación en Proceso | G95: José Andrés Castro Borquez (Gerente TI Corporativo) | H95: jose.castro@cruzdelsur.cl | I95: https://cl.linkedin.com/in/jos%C3%A9-andr%C3%A3%C2%A9s-castro-borquez-0036b2225 | J95: https://cl.linkedin.com/company/gruasyequiposcruzdelsur | L95: Ventas: GRANDE 3 (600.000 - 1.000.000 UF) | Empleados: 278 | T95: 86.117.800-5 | U95: (56) 2 2484 2100
A96: HidroMobile S.A. | B96: Andamios, Plataformas Eléctricas | C96: Santiago | D96: Investigación en Proceso | G96: Fernando Mattus (Jefe de Sistemas Logísticos) | H96: f.mattus@hidromobile.cl | I96: https://cl.linkedin.com/in/fernando-mattus | J96: https://www.linkedin.com/company/comercial-hidromobile-s-a | L96: Ventas: GRANDE 3 (600.000 - 1.000.000 UF) | Empleados: 186 | T96: 99.577.790-8 | U96: (56) 9 824 1284
A97: HidroTattersall | B97: Tratamiento de Riles | C97: Talagante | D97: Investigación en Proceso | G97: Ivan Correa (Gerente General) | H97: i.correa@hidrotattersall.cl | I97: https://cl.linkedin.com/in/ivan-correa-1a99a02a | J97: https://cl.linkedin.com/company/agroriegotattersall | L97: Ventas: GRANDE 3 (600.000 - 1.000.000 UF) | Empleados: 74 | T97: 76517797-9 | U97: (56) 2 3242 4001
A98: Hidronor Chile | B98: Remediación y Saneamiento de Terrenos Contaminados, Revalorización Energética, Recuperación y Reciclaje de Residuos, Transporte, Tratamiento y Disposición final de Residuos | C98: Santiago | D98: Gestión Datos Medioambientales Digital | F98: https://www.hidronor.cl/ | G98: Jorge Stagno (Gerente General) | I98: https://cl.linkedin.com/in/jorge-stagno-9a4a511a | J98: https://www.linkedin.com/company/hidronor | L98: Ventas: GRANDE (Estimado por Empleados) | Empleados: 233 | T98: 96.607.990-8 | U98: (56) 2 2570 5700
A99: Hino Chile | B99: Camiones, Camiones Pesados para Transporte | C99: Santiago | D99: Digitalización Flotas Transporte Pesado | F99: https://www.google.com/search?q=Hino+Chile+Gerente+General+LinkedIn | G99: Antonio Belart Fabbri (Gerente General) | I99: https://cl.linkedin.com/in/antoniobelartfabbri | J99: https://cl.linkedin.com/company/hino-chile-s.a. | L99: Ventas: GRANDE 2 (200.000 - 600.000 UF) | Empleados: 10 | T99: 76.141.853-K | U99: 600 600 2112
A100: Hytera Chile | B100: Radiocomunicaciones, Soluciones de LTE Privado | C100: Santiago | D100: Comunicaciones Críticas (TETRA/DMR) Minería | F100: https://cl.linkedin.com/in/claudio-l%C3%B3pez-410a654a | G100: Claudio López (Ingeniero Superior Campo) | I100: https://cl.linkedin.com/in/claudio-l%C3%B3pez-410a654a | J100: https://cl.linkedin.com/company/hytera | L100: Ventas: GRANDE 2 (200.000 - 600.000 UF) | Empleados: 37 | T100: 76.825.305-6 | U100: (56) 9 3299 4410
...

Sheet CUENTAS_VIP_TOP
A1: Empresa | B1: Rubro | C1: Ciudad | D1: Proyecto / Oportunidad Detectada | E1: Fuente de Información | F1: Enlace a la Fuente | G1: Contacto Sniper | H1: Email de Contacto | I1: Teléfono | J1: Sitio Web | K1: RUT | L1: Contexto Empresa | M1: Categoría Venta | N1: Estado Contacto | O1: Sub-Estado | P1: Fecha Contacto | Q1: Notas CRM | R1: Medio de Contacto | S1: Próximo Seguimiento | T1: Prioridad
A2: A. Hartrodt Chile S.A. | B2: Transporte Aéreo, Transporte Marítimo, Transporte Terrestre | C2: Santiago | D2: Investigación en Proceso | G2: Hector Calderon (Jefe Informática) | H2: hcalderon@hartrodt.cl | I2: (56) 2 2483 7000 | K2: 84.007.300-9 | L2: Ventas: GRANDE 3 (600.000 - 1.000.000 UF) | Empleados: 34 | M2: Tier 1 - OPORTUNIDAD ACTIVA (VIP)
A3: A.J. Broom y Cía. S.A.C. | B3: Agencias Marítimas | C3: Santiago | D3: Plataforma Tracking Marítimo Real-Time | F3: https://www.ajbroom.cl/ | G3: Ricardo Lira (Gerente Operaciones) | I3: (56) 2 2549 8400 | K3: 91.256.000-7 | L3: Ventas: GRANDE 2 (200.000 - 600.000 UF) | Empleados: 33 | M3: Tier 1 - OPORTUNIDAD ACTIVA (VIP)
A4: AB Arriendos S.A. | B4: Arriendo de Equipos para Soldar, Compresores | C4: Santiago | D4: Expansión Arriendo Maquinaria Norte | F4: https://www.abarriendos.cl/ | G4: Roberto Carlos Bailac (Exec. Director) | I4: (56) 2 2351 5400 | K4: 96.872.010-4 | L4: Ventas: GRANDE 2 (200.000 - 600.000 UF) | Empleados: 107 | M4: Tier 1 - OPORTUNIDAD ACTIVA (VIP)
A5: ASAP Group | B5: Recuperación de Campamentos Mineros | C5: Santiago | G5: Gerente de TI / CIO (Director de Tecnología) | I5: (56) 2 2573 0471 | K5: 76.173.088-6 | L5: Ventas: GRANDE 4 (Mas de 1.000.000 UF) | Empleados: 1376 | M5: Tier 1 - VIP (Alta Venta + DM)
A6: ATS Maquinarias | B6: Plataformas Aéreas, Torres de Iluminación | C6: Santiago | G6: Gerente de TI / CIO (Director de Tecnología) | I6: (56) 9 7754 7967 | K6: 99.555.350-3 | L6: Ventas: GRANDE 3 (600.000 - 1.000.000 UF) | Empleados: 38 | M6: Tier 1 - VIP (Alta Venta + DM)
A7: Acciona Energía Chile SpA | B7: Energías Renovables | C7: Santiago | G7: Gerente de TI / CIO (Director de Tecnología) | I7: (56) 2 2751 5160 | K7: 76.492.150-K | L7: Ventas: GRANDE 4 (Mas de 1.000.000 UF) | Empleados: 182 | M7: Tier 1 - VIP (Alta Venta + DM)
A8: Acerorack | B8: Rack Altillo Estructural | C8: Santiago | G8: Gerente de TI / CIO (Director de Tecnología) | I8: (56) 9 9320 7002 | K8: 77.247.510-1 | L8: Ventas: GRANDE 3 (600.000 - 1.000.000 UF) | Empleados: 88 | M8: Tier 1 - VIP (Alta Venta + DM)
A9: Aceros Chilca | B9: Bolas de Acero Forjado para Molienda, Bolas para molienda, Revestimientos para Molinos | C9: Santiago | D9: Modernización Fundición Piezas Mineras | F9: https://www.aceroschilca.com/ | G9: Eduardo Garcia (Country Manager) | I9: (56) 2 2929 5486 | K9: 96.871.960-2 | L9: Ventas: GRANDE 2 (200.000 - 600.000 UF) | Empleados: 4 | M9: Tier 1 - OPORTUNIDAD ACTIVA (VIP)
A10: Acetogen Gas Chile S.A. | B10: Artículos para Seguridad | C10: Santiago | D10: Investigación en Proceso | G10: Hugo Inzulza Daneri (Gerente General) | H10: hinzulza@acetogen.cl | I10: (56) 2 2583 2780 | K10: 93.333.000-1 | L10: Ventas: GRANDE 3 (600.000 - 1.000.000 UF) | Empleados: 57 | M10: Tier 1 - OPORTUNIDAD ACTIVA (VIP)
A11: Adler Steel Chile | B11: Aceros Antiabrasivos, Barras de Aceros Especiales | C11: Santiago | D11: Aceros Especiales Minería (Procesos Críticos) | E11: Portal Minero / Licitaciones | F11: https://adler.cl/wp-content/uploads/2023/06/CatalogoAdlerJunio23.pdf | G11: Sabin Capetillo (Jefe Informática) | H11: scapetillo@adlersteel.cl | I11: (56) 2 2420 5555 | K11: 92.844.000-1 | L11: Ventas: GRANDE 3 (600.000 - 1.000.000 UF) | Empleados: 17 | M11: Tier 1 - OPORTUNIDAD ACTIVA (VIP)
A12: AeroRescate Ambulancias Aéreas | B12: Transporte Aéreo, Transporte Aéreo en Helicóptero | C12: Santiago | D12: Investigación en Proceso | G12: David Acevedo Olguín (Director Corporativo) | H12: dacevedo@dap.cl | I12: (56) 2 3202 6890 | K12: 99.543.620-5 | L12: Ventas: GRANDE 4 (Mas de 1.000.000 UF) | Empleados: 35 | M12: Tier 1 - OPORTUNIDAD ACTIVA (VIP)
A13: Aerocardal Ltda. | B13: Transporte Aéreo en Helicóptero, Vuelos Ambulancia | C13: Santiago | D13: Mantenimiento Digital Embraer (Servicio Autorizado) | E13: Comunicado Embraer / Newsletter | F13: https://tallyho.cl/embraer-suma-a-aerocardal-a-su-red-de-servicios-autorizados-en-chile/ | G13: Javier Arellano (Jefe IT) | H13: jarellano@aerocardal.com | I13: (56) 2 2377 7400 | K13: 78.035.640-5 | L13: Ventas: GRANDE 3 (600.000 - 1.000.000 UF) | Empleados: 98 | M13: Tier 1 - OPORTUNIDAD ACTIVA (VIP)
A14: Aguasin SpA | B14: Sistemas para Purificación de Agua, Tratamiento de Aguas | C14: Santiago | D14: Mantención Telemetría Plantas PW | E14: Mercado Público (ID 4076-121-LE25) | F14: https://www.portalminero.com/noticias/aguasin-y-xylem-presentan-soluciones-digitales-para-el-tratamiento-de-aguas/ | G14: Richard Correa (Gerente Admin (IT Resp)) | H14: rcorrea@aguasin.com | I14: (56) 2 2270 9500 | K14: 76.377.649-2 | L14: Ventas: GRANDE 4 (Mas de 1.000.000 UF) | Empleados: 174 | M14: Tier 1 - OPORTUNIDAD ACTIVA (VIP)
A15: Agunsa, Agencias Universales S.A. | B15: Agencias de Carga, Almacenamiento de Carga, Transporte de Minerales | C15: Santiago | D15: Estrategia Global Innovación Digital | E15: LinkedIn | F15: https://cl.linkedin.com/in/carlos-ram%C3%ADrez-c%C3%A1rdenas-8b9b2b2a | G15: Carlos Ramírez (CTO Corporativo) | I15: (56) 2 2460 2700 | K15: 96.566.940-K | L15: Ventas: GRANDE (Estimado por Empleados) | Empleados: 796 | M15: Tier 1 - OPORTUNIDAD ACTIVA (VIP)
A16: Aislapol S.A. | B16: Aislantes Térmicos, Envases de Plástico | C16: Santiago | G16: Gerente de TI / CIO (Director de Tecnología) | I16: (56) 2 2670 0105 | K16: 76.412.645-9 | L16: Ventas: GRANDE 4 (Mas de 1.000.000 UF) | Empleados: 358 | M16: Tier 1 - VIP (Alta Venta + DM)
A17: Alessandri & Cía. Ltda. | B17: Asesorías Jurídicas en Minería, Servicios Legales | C17: Santiago | D17: Implementación LegalTech & Ciberseguridad | F17: https://cl.linkedin.com/in/francisco-fern%C3%A1ndez-mancilla | G17: Francisco Javier Fernández M. (Subgerente Ops) | I17: (56) 2 2787 6000 | K17: 79.784.430-6 | L17: Ventas: GRANDE 3 (600.000 - 1.000.000 UF) | Empleados: 101 | M17: Tier 1 - OPORTUNIDAD ACTIVA (VIP)
A18: Alfa People Chile SpA | B18: Diseño de Sistemas ERP | C18: Santiago | D18: Proyectos Microsoft Dynamics 365 Cloud | F18: https://alfapeople.com/cl/ | G18: Carlos Amaro (CEO) | I18: (56) 2 2751 9000 | K18: 76.360.577-9 | L18: Ventas: GRANDE 3 (600.000 - 1.000.000 UF) | Empleados: 121 | M18: Tier 1 - OPORTUNIDAD ACTIVA (VIP)
A19: Aliservice | B19: Alimentación Industrial | C19: Santiago | D19: Digitalización Cadena Suministro Alimentación | F19: https://www.aliservice.cl/ | G19: Luis Alberto Santana (Gerente Adm y Finanzas) | I19: (56) 2 2913 5500 | K19: 76437608-0 | L19: Ventas: GRANDE 3 (600.000 - 1.000.000 UF) | Empleados: 1372 | M19: Tier 1 - OPORTUNIDAD ACTIVA (VIP)
A20: American Parts | B20: Actividades de Apoyo para la Explotación de Minas y Canteras, Venta de Partes, Piezas y Accesorios para Vehículos Automotores | C20: Antofagasta | D20: Canal E-commerce B2B (Expansión Digital) | E20: Americanparts.cl / LinkedIn | F20: https://americanparts.cl/shop/ | G20: Patricio Herrera (Jefe de Sistemas) | H20: p.herrera@americanparts.cl | I20: (56) 9 4220 1935 | J20: http://www.americanparts.cl | K20: 76.790.684-6 | L20: Ventas: GRANDE 3 (600.000 - 1.000.000 UF) | Empleados: 38 | M20: Tier 1 - OPORTUNIDAD ACTIVA (VIP)
A21: Anakena Group | B21: Construcciones Modulares, Servicios Hoteleros | C21: Santiago | D21: Hotelería Modular Minería (Sistemas Gestión) | E21: Exponor 2024 / BCN | F21: https://www.anakenagroup.cl/2024/06/10/anakena-noticias/ | G21: Michael Salameh (Jefe de Sistemas Producción) | H21: m.salameh@anakena.cl | I21: (56) 2 2951 5328 | K21: 52.003.237-1 | L21: Ventas: GRANDE 3 (600.000 - 1.000.000 UF) | Empleados: 476 | M21: Tier 1 - OPORTUNIDAD ACTIVA (VIP)
A22: Ancor Tecmin | B22: Aisladores para Anodos y Cátodos, Celdas Electrolíticas | C22: Santiago | D22: Investigación en Proceso | G22: Franco Yáñez (Jefe Automatización e Informática) | H22: f.yanez@ancortecmin.cl | I22: (56) 2 2510 6000 | K22: 76.411.929-0 | L22: Ventas: GRANDE 3 (600.000 - 1.000.000 UF) | Empleados: 191 | M22: Tier 1 - OPORTUNIDAD ACTIVA (VIP)
A23: Andes Solar | B23: Desarrollo, Construcción y Operación de Proyectos de Energía Renovable | C23: Santiago | D23: Investigación en Proceso | G23: Felipe Aguilera Moore (Jefe de Ingeniería) | H23: f.aguilera@andessolar.cl | I23: (56) 2 2956 6230 | K23: 76.271.321-7 | L23: Ventas: GRANDE 3 (600.000 - 1.000.000 UF) | Empleados: 95 | M23: Tier 1 - OPORTUNIDAD ACTIVA (VIP)
A24: Andinor Perforaciones Ltda. | B24: Captación de Aguas Subterráneas | C24: Santiago | G24: Gerente de TI / CIO (Director de Tecnología) | I24: (56) 2 2719 3808 | K24: 76.271.472-8 | L24: Ventas: GRANDE 3 (600.000 - 1.000.000 UF) | Empleados: 210 | M24: Tier 1 - VIP (Alta Venta + DM)
A25: Anglo American Chile | B25: Anodos de Cobre, Cátodos de Cobre, Concentrado de Molibdeno, Sulfato de Cobre | C25: Santiago | D25: Centro Remoto IROC | E25: LinkedIn | F25: https://cl.linkedin.com/in/rodrigosubiabre | G25: Rodrigo Subiabre (VP Tech & Innov) | I25: (56) 2 2230 6000 | K25: 77.905.330-K | L25: Ventas: GRANDE (Estimado por Empleados) | Empleados: 837 | M25: Tier 1 - OPORTUNIDAD ACTIVA (VIP)
A26: Anser Mining SpA | B26: Plantas Seleccionadoras Móviles | C26: Santiago | G26: Gerente de TI / CIO (Director de Tecnología) | I26: (56) 2 2435 4615 | K26: 76253942-K | L26: Ventas: GRANDE 3 (600.000 - 1.000.000 UF) | Empleados: 260 | M26: Tier 1 - VIP (Alta Venta + DM)
A27: Anval S.A. | B27: Sistemas de Pesaje Hidráulico, Sistemas para Control de Maquinarias, Sistemas para Manejo de Materiales | C27: Santiago | G27: Gerente de TI / CIO (Director de Tecnología) | I27: (56) 2 2951 6907 | K27: 76.746.640-4 | L27: Ventas: GRANDE 3 (600.000 - 1.000.000 UF) | Empleados: 24 | M27: Tier 1 - VIP (Alta Venta + DM)
A28: Análisis Ambientales S.A. | B28: Tratamiento de Aguas Servidas | C28: Santiago | G28: Gerente de TI / CIO (Director de Tecnología) | I28: (56) 2 2569 4400 | K28: 96.967.550-1 | L28: Ventas: GRANDE 3 (600.000 - 1.000.000 UF) | Empleados: 353 | M28: Tier 1 - VIP (Alta Venta + DM)
A29: Artilec Ltda. | B29: Cámaras IP para Vigilancia, Seguridad Industrial y Minera | C29: Santiago | D29: Investigación en Proceso | G29: Mayron Araya (Soporte Informática) | H29: maraya@artilec.cl | I29: (56) 2 2240 7500 | K29: 79.796.310-0 | L29: Ventas: GRANDE 3 (600.000 - 1.000.000 UF) | Empleados: 67 | M29: Tier 1 - OPORTUNIDAD ACTIVA (VIP)
A30: Asesorías Algoritmos y Mediciones Ambientales SpA | B30: Servicios de Ingeniería | C30: Santiago | G30: Gerente de TI / CIO (Director de Tecnología) | I30: (56) 2 2361 6600 | K30: 77.007.600-5 | L30: Ventas: GRANDE 3 (600.000 - 1.000.000 UF) | Empleados: 437 | M30: Tier 1 - VIP (Alta Venta + DM)
A31: AtPac Doka | B31: Andamios | C31: Santiago | D31: Encofrados & Seguridad Construcción | F31: https://www.google.com/search?q=AtPac+Doka+Chile+LinkedIn | G31: Aldo Veas (Technical Manager LATAM) | I31: (56) 9 3394 1026 | K31: 77.383.881-K | L31: Ventas: GRANDE 2 (200.000 - 600.000 UF) | Empleados: 43 | M31: Tier 1 - OPORTUNIDAD ACTIVA (VIP)
A32: Atco Sabinco | B32: Construcciones Modulares | C32: Santiago | G32: Gerente de TI / CIO (Director de Tecnología) | I32: (56) 2 2391 9800 | K32: 76.175.835-7 | L32: Ventas: GRANDE 4 (Mas de 1.000.000 UF) | Empleados: 949 | M32: Tier 1 - VIP (Alta Venta + DM)
A33: Atlas Renewable Energy | B33: Plantas de Energía Solar | C33: Santiago | D33: Investigación en Proceso | G33: Francisca Latorre H. (Corporate IT Manager) | H33: flatorre@atlasrenewableenergy.com | I33: (56) 2 2611 8300 | K33: 76376627-6 | L33: Ventas: GRANDE 3 (600.000 - 1.000.000 UF) | Empleados: 0 | M33: Tier 1 - OPORTUNIDAD ACTIVA (VIP)
A34: Attex Ltda. | B34: Spools, Tubos de Acero | C34: Santiago | G34: Gerente de TI / CIO (Director de Tecnología) | I34: (56) 2 2924 1750 | K34: 85.257.700-2 | L34: Ventas: GRANDE 3 (600.000 - 1.000.000 UF) | Empleados: 45 | M34: Tier 1 - VIP (Alta Venta + DM)
A35: Austin Powder Chile | B35: Detonantes Electrónicos, Servicios para Tronaduras | C35: Santiago | G35: Gerente de TI / CIO (Director de Tecnología) | I35: (56) 2 2374 0030 | K35: 96.511.470-K | L35: Ventas: GRANDE 3 (600.000 - 1.000.000 UF) | Empleados: 68 | M35: Tier 1 - VIP (Alta Venta + DM)
A36: Avery Dennison Chile S.A. | B36: Seguridad Industrial y Minera | C36: Santiago | G36: Gerente de TI / CIO (Director de Tecnología) | I36: (56) 2 2898 8063 | K36: 96.721.090-0 | L36: Ventas: GRANDE 4 (Mas de 1.000.000 UF) | Empleados: 62 | M36: Tier 1 - VIP (Alta Venta + DM)
A37: Axinntus Ltda. | B37: Servicios de Limpieza Industrial | C37: Antofagasta | G37: Gerente de TI / CIO (Director de Tecnología) | I37: (56) 32 220 2975 | K37: 76.189.625-3 | L37: Ventas: GRANDE 4 (Mas de 1.000.000 UF) | Empleados: 988 | M37: Tier 1 - VIP (Alta Venta + DM)
A38: B y M Agencia Marítima S.A. | B38: Agencias Marítimas | C38: Santiago | G38: Gerente de TI / CIO (Director de Tecnología) | I38: (56) 2 2347 2100 | K38: 78.986.820-4 | L38: Ventas: GRANDE 3 (600.000 - 1.000.000 UF) | Empleados: 132 | M38: Tier 1 - VIP (Alta Venta + DM)
A39: BASF Chile S.A. | B39: Productos Químicos para la Minería | C39: Santiago | D39: Transformación Digital Clusters Región Andes | F39: https://cl.linkedin.com/in/jonathan-rojas-diaz | G39: Jonathan Rojas (Gerente Digitalización) | I39: (56) 2 2640 7000 | K39: 80.043.600-1 | L39: Ventas: GRANDE (Estimado por Empleados) | Empleados: 256 | M39: Tier 1 - OPORTUNIDAD ACTIVA (VIP)
A40: BC Bearing Chile S.A. | B40: Acoplamientos Flexibles, Poleas, Rodamientos | C40: Santiago | G40: Gerente de TI / CIO (Director de Tecnología) | I40: (56) 2 2351 5332 | K40: 96.678.530-6 | L40: Ventas: GRANDE 3 (600.000 - 1.000.000 UF) | Empleados: 51 | M40: Tier 1 - VIP (Alta Venta + DM)
A41: BFS Chile | B41: Proveedor Destacado, Dataloggers, Equipos Contra Incendio, Equipos de Monitoreo y Telegestión, Plantas de Tratamiento de Agua, Sistemas de Filtración, Válvulas de Control, Válvulas de Corte y Similares, Válvulas de Venteo | C41: Santiago | G41: Gerente de TI / CIO (Director de Tecnología) | I41: (56) 2 2489 5100 | J41: http://www.bfschile.com | K41: 96.808.700-2 | L41: Ventas: GRANDE 3 (600.000 - 1.000.000 UF) | Empleados: 91 | M41: Tier 1 - VIP (Alta Venta + DM)
A42: Bailac | B42: Aros y Llantas para Camiones, Reciclaje de Neumáticos OTR | C42: Santiago | D42: Tecnología Gestión Neumáticos & Economía Circular | F42: https://cl.linkedin.com/in/raimundo-bailac-pereira-b53269104 | G42: Raimundo Bailac (GG) | I42: (56) 2 2915 9130 | K42: 79.722.740-4 | L42: Ventas: GRANDE 2 (200.000 - 600.000 UF) | Empleados: 95 | M42: Tier 1 - OPORTUNIDAD ACTIVA (VIP)
A43: Bailac Thor Saan Ltda. | B43: Recauchaje de Neumáticos, Servicios de Reparación de Neumáticos Gigantes a la Minería | C43: Iquique | D43: Tecnología Gestión Neumáticos & Economía Circular | F43: https://cl.linkedin.com/in/raimundo-bailac-pereira-b53269104 | G43: Raimundo Bailac (GG) | I43: (56) 57 251 8300 | K43: 78.080.330-4 | L43: Ventas: GRANDE 3 (600.000 - 1.000.000 UF) | Empleados: 156 | M43: Tier 1 - OPORTUNIDAD ACTIVA (VIP)
A44: Baker McKenzie, Servicios Legales SpA | B44: Asesorías Jurídicas en Minería, Servicios Legales | C44: Santiago | G44: Gerente de TI / CIO (Director de Tecnología) | I44: (56) 2 2367 7000 | K44: 76.451.566-8 | L44: Ventas: GRANDE 3 (600.000 - 1.000.000 UF) | Empleados: 56 | M44: Tier 1 - VIP (Alta Venta + DM)
A45: Barraca de Fierro San Joaquín SpA | B45: Barracas de Acero, Barracas de Fierros | C45: Santiago | D45: Transformación Digital Ventas & Inventario | F45: https://cl.linkedin.com/in/martin-vera-0b1a1b1b | G45: Martín Vera (CIO/CTO) | I45: (56) 2 2551 6867 | K45: 96.654.030-3 | L45: Ventas: GRANDE 2 (200.000 - 600.000 UF) | Empleados: 21 | M45: Tier 1 - OPORTUNIDAD ACTIVA (VIP)
A46: Bartech | B46: Capturadores de Información, Control de Accesos | C46: Santiago | D46: Investigación en Proceso | G46: Raul Lara (Gerente Comercial y Desarrollo) | H46: raul.lara@bartech.cl | I46: (56) 2 2923 8600 | K46: 99.539.070-1 | L46: Ventas: GRANDE 3 (600.000 - 1.000.000 UF) | Empleados: 20 | M46: Tier 1 - OPORTUNIDAD ACTIVA (VIP)
A47: Basalto Drilling | B47: Servicios de Perforación, Sondajes Diamantinos | C47: Santiago | G47: Gerente de TI / CIO (Director de Tecnología) | I47: (56) 2 3216 6092 | K47: 76472652-9 | L47: Ventas: GRANDE 3 (600.000 - 1.000.000 UF) | Empleados: 170 | M47: Tier 1 - VIP (Alta Venta + DM)
A48: Bechtel Chile Ltda. | B48: Construcción de Plantas Mineras | C48: Santiago | D48: Sistemas IT Ingeniería Minería & Infraestructura | F48: https://cl.linkedin.com/in/felipe-espinoza-yentzen-377a3b67 | G48: Felipe Espinoza (Infrastructure Lead) | I48: (56) 2 2675 1000 | K48: 95.207.000-2 | L48: Ventas: GRANDE (Estimado por Empleados) | Empleados: 1820 | M48: Tier 1 - OPORTUNIDAD ACTIVA (VIP)
A49: Beiben Truck | B49: Bulldozers, Camiones Carreteros y Fuera de Carretera (OTR) | C49: Santiago | D49: Camiones Autónomos para Minería | F49: https://cl.linkedin.com/in/philipp-kaufmann-beiben-truck-94828180 | G49: Philipp Kaufmann (CEO) | I49: (56) 2 2797 6200 | K49: 76.077.627-0 | L49: Ventas: GRANDE 2 (200.000 - 600.000 UF) | Empleados: 13 | M49: Tier 1 - OPORTUNIDAD ACTIVA (VIP)
A50: Beka | B50: Plantas Dosificadoras para Hormigón | C50: Santiago | G50: Gerente de TI / CIO (Director de Tecnología) | I50: (56) 2 2753 6700 | K50: 76.108.278-7 | L50: Ventas: GRANDE 3 (600.000 - 1.000.000 UF) | Empleados: 66 | M50: Tier 1 - VIP (Alta Venta + DM)
A51: Bertech | B51: Productos Químicos para la Mantención de Equipos Mineros, Productos Químicos para la Minería, Revestimientos Industriales | C51: Santiago | D51: Transf. Digital Revestimientos Industriales | F51: https://cl.linkedin.com/in/pedro-fernandez-parraguez | G51: Pedro Fernández Parraguez (IT Manager) | I51: (56) 2 2246 3485 | K51: 76.054.686-0 | L51: Ventas: GRANDE 2 (200.000 - 600.000 UF) | Empleados: 152 | M51: Tier 1 - OPORTUNIDAD ACTIVA (VIP)
A52: Biggi (Chile) S.A. | B52: Cocinas Industriales, Equipos para Preparar Alimentos | C52: Santiago | D52: IoT Equipamiento Cocinas Industriales | F52: https://www.biggi.cl/ | G52: Sergio Biggi (Gerente General) | I52: (56) 2 2412 6200 | K52: 91.462.001-5 | L52: Ventas: GRANDE 2 (200.000 - 600.000 UF) | Empleados: 6 | M52: Tier 1 - OPORTUNIDAD ACTIVA (VIP)
A53: Bignotti Hermanos S.A. | B53: Equipos para Refinerías Electrolíticas | C53: Santiago | G53: Gerente de TI / CIO (Director de Tecnología) | I53: (56) 2 2836 4400 | K53: 80.113.000-3 | L53: Ventas: GRANDE 3 (600.000 - 1.000.000 UF) | Empleados: 103 | M53: Tier 1 - VIP (Alta Venta + DM)
A54: Bimex Ltda. | B54: Equipos Eléctricos | C54: Santiago | D54: Modernización Sistemas LIS Laboratorio | F54: https://www.bimex.cl/ | G54: Alberto Harrison (General Manager) | I54: (56) 2 2306 2200 | K54: 78.836.730-9 | L54: Ventas: GRANDE 2 (200.000 - 600.000 UF) | Empleados: 9 | M54: Tier 1 - OPORTUNIDAD ACTIVA (VIP)
A55: Biofiltro | B55: Plantas de Tratamiento de Aguas Servidas | C55: Santiago | D55: Automatización Tratamiento Riles (Sistema BIDA) | F55: https://cl.linkedin.com/in/ignacio-andr%C3%A9s-jofr%C3%A9-valenzuela-69902289 | G55: Ignacio Jofré Valenzuela (Subgerente Proyectos) | I55: (56) 2 3224 3648 | K55: 76.337.422-K | L55: Ventas: GRANDE 2 (200.000 - 600.000 UF) | Empleados: 86 | M55: Tier 1 - OPORTUNIDAD ACTIVA (VIP)
A56: Biotec Chile S.A. | B56: Detergentes | C56: Santiago | D56: Investigación en Proceso | G56: Fabián Deramond (Gerente TI y Transf. Digital) | H56: f.deramond@biotec.cl | I56: (56) 2 2963 4500 | K56: 96.025.000-1 | L56: Ventas: GRANDE 3 (600.000 - 1.000.000 UF) | Empleados: 77 | M56: Tier 1 - OPORTUNIDAD ACTIVA (VIP)
A57: Blumos Ltda. | B57: Tratamiento de Aguas | C57: Santiago | G57: Gerente de TI / CIO (Director de Tecnología) | I57: (56) 2 2947 3300 | K57: 82.705.900-5 | L57: Ventas: GRANDE 4 (Mas de 1.000.000 UF) | Empleados: 112 | M57: Tier 1 - VIP (Alta Venta + DM)
A58: Bombas de Pozo Ltda. | B58: Proveedor Destacado, Accesorios para Perforación, Asesorías, Bombas para Pozos Profundos, Bombas Sumergibles, Bombas Sumergibles para Pozos Profundos, Cables Sumergibles, Cañerías con Hilo, Coplas y Abrazaderas, Reparación de Equipos Hidráulicos, Servicio Técnico, Tableros Eléctricos, Tuberías Flexibles para Pozos Profundos | C58: Santiago | D58: Investigación en Proceso | G58: Mauricio Illanes (Socio Técnico) | H58: m.illanes@bombasdepozo.cl | I58: (56) 2 2842 0700 | J58: http://www.bombasdepozo.cl | K58: 78.176.700-K | L58: Ventas: GRANDE 3 (600.000 - 1.000.000 UF) | Empleados: 36 | M58: Tier 1 - OPORTUNIDAD ACTIVA (VIP)
A59: Bosch Rexroth Chile | B59: Bulldozers, Cargadoras Retroexcavadoras | C59: Santiago | D59: Monitoreo Predictivo | E59: Catálogo Soluciones | F59: https://www.boschrexroth.com/es/cl/noticias-e-historias/mineria/soluciones-bosch-rexroth-para-mineria/ | G59: Oscar Torres (Jefe Proyectos TI) | H59: oscar.torres@boschrexroth.cl | I59: (56) 2 2487 3700 | K59: 76.365.959-3 | L59: Ventas: GRANDE 4 (Mas de 1.000.000 UF) | Empleados: 79 | M59: Tier 1 - OPORTUNIDAD ACTIVA (VIP)
A60: Bottai S.A. | B60: Prefabricados de Concreto y Hormigón, Tubos de Concreto y Hormigón | C60: Santiago | D60: Investigación en Proceso | G60: Rodrigo Gimenez Fernandez (Gerente Comercial) | H60: r.gimenez@bottai.cl | I60: (56) 2 2413 1200 | K60: 80.125.100-5 | L60: Ventas: GRANDE 3 (600.000 - 1.000.000 UF) | Empleados: 384 | M60: Tier 1 - OPORTUNIDAD ACTIVA (VIP)
A61: Bradken Chile | B61: Revestimientos para Molinos | C61: Santiago | D61: Investigación en Proceso | G61: Juan Carlos Rojas (IT Manager) | H61: j.rojas@bradken.com | K61: 76980920-1 | L61: Ventas: GRANDE 3 (600.000 - 1.000.000 UF) | Empleados: 28 | M61: Tier 1 - OPORTUNIDAD ACTIVA (VIP)
A62: Budge Chile SpA | B62: Transmisiones Mecánicas | C62: Iquique | D62: Modernización Grid & Software Energía | F62: https://www.ge.com/news/reports/ge-chile-100-years | G62: Rodrigo Elizondo (CEO Chile) | I62: (56) 2 2885 4224 | K62: 76.869.432-K | L62: Ventas: GRANDE 1 (100.000 - 200.000 UF) | Empleados: 3 | M62: Tier 1 - OPORTUNIDAD ACTIVA (VIP)
A63: CEIM - Centro de Entrenamiento Industrial y Minero | B63: Proveedor Destacado, Capacitación, Capacitación de Personal, Capacitación de Soldadores, Capacitación en Especialidades Mineras, Capacitación en Mantenimiento de Equipos Pesados, Capacitación en Operación de Equipos Mineros, Capacitación en Operación de Grúas, Capacitación en Operación de Plantas Mineras, Capacitación en Seguridad y Psicolaboral, Educación para la Minería | C63: Antofagasta | D63: Digitalización Capacitación Minera | F63: https://www.ceim.cl/ | G63: Milton Flores (Gerente Desarrollo Competencias) | I63: (56) 55 245 6001 | J63: http://www.ceim.cl | K63: 74.191.400-K | L63: Ventas: GRANDE 3 (600.000 - 1.000.000 UF) | Empleados: 184 | M63: Tier 1 - OPORTUNIDAD ACTIVA (VIP)
A64: CEIM Ltda. - Certificaciones y Servicios | B64: Proveedor Destacado, Asesorías en Mecánica, Asesorías en Minería, Asesorías en Procesos Mineros, Asesorías en Proyectos Industriales, Asesorías en Seguridad, Certificación de Competencias Laborales, Certificación de Equipos Mineros, Certificación de Grúas, Certificación de Operadores de Maquinarias y Equipos | C64: Antofagasta | D64: Digitalización Capacitación Minera | F64: https://www.ceim.cl/ | G64: Milton Flores (Gerente Desarrollo Competencias) | I64: (56) 55 245 6000 | J64: http://www.ceim.cl | K64: 76.613.900-0 | L64: Ventas: GRANDE 3 (600.000 - 1.000.000 UF) | Empleados: 102 | M64: Tier 1 - OPORTUNIDAD ACTIVA (VIP)
A65: CGE C | B65: Alumbrado Público y Privado (aéreo y subterráneo), Corrientes Débiles, Empalmes, Redes Aéreas y Subterráneas, Sistemas para Aumento de Potencia, Venta, Arriendo e Instalación de Equipos Eléctricos | C65: Santiago | D65: Digitalización Redes | E65: LinkedIn CDO | F65: https://cl.linkedin.com/in/cristian-ormazabal | G65: Cristian Ormazábal (Chief Digital Officer (CDO)) | H65: cormazabal@cge.cl | I65: (56) 2 2280 7400 | K65: 77.316.204-2 | L65: Ventas: GRANDE 4 (Mas de 1.000.000 UF) | Empleados: 52 | M65: Tier 1 - OPORTUNIDAD ACTIVA (VIP)
A66: Canon Chile S.A. | B66: Equipos para Oficina | C66: Santiago | D66: Gestión Documental Cloud | E66: Estrategia Regional 2025 | F66: https://www.canon.cl/blog/fortaleciendo-alianzas-y-estrategias-de-negocios-canon-reunio-sus-canales-regionales-en-su | G66: Aaron Fuentes Calderón (Gerente de TI) | H66: afuentes@canon.cl | I66: (56) 2 2477 6200 | K66: 96.716.060-1 | L66: Ventas: GRANDE 4 (Mas de 1.000.000 UF) | Empleados: 138 | M66: Tier 1 - OPORTUNIDAD ACTIVA (VIP)
A67: Caxtor | B67: Energía Solar | C67: Santiago | D67: Modernización Infraestructura Telecom & Marítima | F67: https://cl.linkedin.com/company/grupo-caxtor | G67: Brian Smith Hanne (Gte Comercial) | I67: (56) 2 2791 9662 | K67: 76.152.409-7 | L67: Ventas: GRANDE 2 (200.000 - 600.000 UF) | Empleados: 36 | M67: Tier 1 - OPORTUNIDAD ACTIVA (VIP)
A68: Centro Médico del Trabajador (CMT) | B68: Proveedor Destacado, Centro Médico de Salud Ocupacional, Centros Médicos, Reclutamiento y Selección | C68: Santiago | D68: Transformación Digital Salud Ocupacional | F68: https://cl.linkedin.com/in/ignacio-henderson-gonzalez-08108754 | G68: Ignacio Henderson Gonzalez (Director Innovación) | I68: (56) 2 2634 2492 | J68: http://www.cmtsalud.cl | K68: 76.247.147-7 | L68: Ventas: GRANDE 3 (600.000 - 1.000.000 UF) | Empleados: 388 | M68: Tier 1 - OPORTUNIDAD ACTIVA (VIP)
A69: Christensen Chile S.A. | B69: Aditivos para Sondajes Mineros, Cromado Industrial | C69: Santiago | G69: Gerente de TI / CIO (Director de Tecnología) | I69: (56) 2 2620 7847 | K69: 96.515.290-3 | L69: Ventas: GRANDE 4 (Mas de 1.000.000 UF) | Empleados: 198 | M69: Tier 1 - VIP (Alta Venta + DM)
A70: Clemsa | B70: Camiones, Cargadores Frontales | C70: Santiago | G70: Gerente de TI / CIO (Director de Tecnología) | I70: (56) 2 2510 8100 | K70: 94.836.000-4 | L70: Ventas: GRANDE 4 (Mas de 1.000.000 UF) | Empleados: 133 | M70: Tier 1 - VIP (Alta Venta + DM)
A71: Codelco Chile División Salvador | B71: Barro Anódico, Cátodos de Cobre, Cobre, Concentrado de Cobre, Plata | C71: El Salvador | D71: Digitalización Faenas | E71: Reporte Integrado 2024 | F71: https://www.codelco.com/sustentabilidad/reporte-integrado | G71: José Ramón Abatte (Gerente Corp Tecnología) | H71: jabatte@codelco.cl | I71: (56) 52 247 2514 | K71: 61.704.000-K | L71: Ventas: GRANDE (Estimado por Empleados) | Empleados: 16946 | M71: Tier 1 - OPORTUNIDAD ACTIVA (VIP)
A72: Comaco Servicios Logísticos SpA | B72: Arriendo de Grúas, Arriendo de Grúas Horquilla | C72: Santiago | D72: Continuidad Operativa Plantas | E72: LinkedIn | F72: https://cl.linkedin.com/in/ariel-viveros-s%C3%A1ez-a2883650 | G72: Ariel Viveros Sáez (Jefe Proyectos TI) | I72: (56) 2 2222 3192 | K72: 99.587.850-K | L72: Ventas: GRANDE 2 (200.000 - 600.000 UF) | Empleados: 61 | M72: Tier 1 - OPORTUNIDAD ACTIVA (VIP)
A73: Comercial Aragón S.A. | B73: Desarrollo de Proyectos Eléctricos | C73: Santiago | G73: Gerente de TI / CIO (Director de Tecnología) | I73: (56) 2 2495 3000 | K73: 78.430.830-8 | L73: Ventas: GRANDE 4 (Mas de 1.000.000 UF) | Empleados: 127 | M73: Tier 1 - VIP (Alta Venta + DM)
A74: Comercial Sinsef Ltda. | B74: Aislantes Térmicos, Empaquetaduras, Sellos Mecánicos | C74: Concepción | G74: Gerente de TI / CIO (Director de Tecnología) | I74: (56) 41 248 5656 | K74: 78.292.360-9 | L74: Ventas: GRANDE 3 (600.000 - 1.000.000 UF) | Empleados: 55 | M74: Tier 1 - VIP (Alta Venta + DM)
A75: Comgrap Ltda. / 3D - BIM | B75: Software para Control de Proyectos, Software para la Minería, Software para Mantenimiento de Plantas Mineras | C75: Santiago | D75: DigitalHub LMS & Estándares BIM ISO 19650 | E75: Comgrap.cl | G75: Ricardo Rizzi Limone (Gerente General) | H75: rrizzi@comgrap.cl | I75: (56) 2 2592 9000 | K75: 79.770.640-K | L75: Ventas: GRANDE 3 (600.000 - 1.000.000 UF) | Empleados: 37 | M75: Tier 1 - OPORTUNIDAD ACTIVA (VIP)
A76: Consorcio Santa Marta S.A. | B76: Plantas para Tratamiento de Riles, Rellenos Sanitarios | C76: Santiago | G76: Gerente de TI / CIO (Director de Tecnología) | I76: (56) 2 2592 1234 | K76: 96.828.810-5 | L76: Ventas: GRANDE 4 (Mas de 1.000.000 UF) | Empleados: 505 | M76: Tier 1 - VIP (Alta Venta + DM)
A77: Constructora Inarco S.A. | B77: Construcción de Obras Civiles, Construcción Industrial | C77: Santiago | D77: Digitalización BIM & Workflows CMS | F77: https://cl.linkedin.com/in/hugo-mu%C3%B1oz-b587061a | G77: Hugo Muñoz (SubGerente TI) | I77: (56) 2 2240 8400 | K77: 96.513.310-0 | L77: Ventas: GRANDE (Estimado por Empleados) | Empleados: 1654 | M77: Tier 1 - OPORTUNIDAD ACTIVA (VIP)
A78: DB Schenker Chile | B78: Transporte Aéreo, Transporte Marítimo, Transporte Terrestre | C78: Santiago | G78: Gerente de TI / CIO (Director de Tecnología) | I78: (56) 2 3210 4630 | K78: 78.141.230-9 | L78: Ventas: GRANDE 4 (Mas de 1.000.000 UF) | Empleados: 221 | M78: Tier 1 - VIP (Alta Venta + DM)
A79: Danfoss Chile Ltda. | B79: Bombas, Convertidores de Frecuencia | C79: Santiago | G79: Gerente de TI / CIO (Director de Tecnología) | I79: (56) 2 2897 8800 | K79: 78.923.930-4 | L79: Ventas: GRANDE 4 (Mas de 1.000.000 UF) | Empleados: 31 | M79: Tier 1 - VIP (Alta Venta + DM)
A80: Datamine | B80: Consultoría en Minería, Software | C80: Santiago | D80: Transf. Digital & Software Eficiencia Minera | F80: https://cl.linkedin.com/in/elio-cespedes-b-61763331 | G80: Elio Cespedes B (Gerente General Hispanoamerica) | I80: (56) 2 2963 9920 | K80: 96.783.640-0 | L80: Ventas: GRANDE 2 (200.000 - 600.000 UF) | Empleados: 72 | M80: Tier 1 - OPORTUNIDAD ACTIVA (VIP)
A81: Diexa S.A. | B81: Sistemas para Tronaduras | C81: Santiago | G81: Gerente de TI / CIO (Director de Tecnología) | I81: (56) 2 2728 0004 | K81: 99.505.900-2 | L81: Ventas: GRANDE 4 (Mas de 1.000.000 UF) | Empleados: 397 | M81: Tier 1 - VIP (Alta Venta + DM)
A82: Drillco S.A. | B82: Brocas | C82: Santiago | G82: Gerente de TI / CIO (Director de Tecnología) | I82: (56) 2 2431 2200 | K82: 88.859.600-3 | L82: Ventas: GRANDE 4 (Mas de 1.000.000 UF) | Empleados: 141 | M82: Tier 1 - VIP (Alta Venta + DM)
A83: Dräger Chile | B83: Equipos de Emergencia, Equipos de Protección Personal (EPP), Equipos de Protección Respiratoria | C83: Santiago | G83: Gerente de TI / CIO (Director de Tecnología) | I83: 600 006 0001 | K83: 76.033.880-K | L83: Ventas: GRANDE 4 (Mas de 1.000.000 UF) | Empleados: 143 | M83: Tier 1 - VIP (Alta Venta + DM)
A84: Dyno Nobel Explosivos Chile | B84: Proveedor Destacado, Administración de Polvorines, Asistencia Técnica de Tronadura, Asistencia Técnica Geomecánica, Servicios de Tronadura | C84: Santiago | D84: Cibersegurida Industrial | E84: LinkedIn CIO | G84: Julio Solari (CIO & CISO) | H84: julio.solari@am.dynonobel.com | I84: (56) 9 3924 1455 | J84: http://www.dynonobel.lat | K84: 76.040.923-5 | L84: Ventas: GRANDE 4 (Mas de 1.000.000 UF) | Empleados: 158 | M84: Tier 1 - OPORTUNIDAD ACTIVA (VIP)
A85: ELB - Transportes Libertador | B85: Proveedor Destacado, Transporte de Carga por Carretera, Transporte de Carga Sobredimensionada, Transporte de Cargas Especiales, Transporte de Maquinaria, Transporte de NFU, Transporte en Faena (Home Delivery), Transporte para la Minería | C85: Santiago | D85: Investigación en Proceso | G85: Miguel Angel Vergara (Jefe de Sistemas) | H85: mvergara@elb.cl | I85: (56) 9 9344 0371 | J85: http://www.elb.cl | K85: 79.554.850-5 | L85: Ventas: GRANDE 3 (600.000 - 1.000.000 UF) | Empleados: 212 | M85: Tier 1 - OPORTUNIDAD ACTIVA (VIP)
A86: EPM Chile S.A. | B86: Proyectos para Infraestructura | C86: Santiago | D86: Investigación en Proceso | G86: Fernando Meza (Gerente General (Tech Decision Maker)) | H86: fmeza@epmchile.cl | I86: (56) 2 2953 6631 | K86: 76.266.933-1 | L86: Ventas: GRANDE 3 (600.000 - 1.000.000 UF) | Empleados: 3 | M86: Tier 1 - OPORTUNIDAD ACTIVA (VIP)
A87: Eaton Chile | B87: Salas Eléctricas, Tableros Eléctricos | C87: Santiago | D87: Fabricación Electrónica para Proyectos EPC | F87: https://cl.linkedin.com/in/miguel-gonzalez-moraga-b3a91962 | G87: Miguel Gonzalez Moraga (Project Manager) | I87: (56) 2 2640 8165 | K87: 76.103.571-1 | L87: Ventas: GRANDE (Estimado por Empleados) | Empleados: 437 | M87: Tier 1 - OPORTUNIDAD ACTIVA (VIP)
A88: Ecopreneur Chile S.A. | B88: Contratos Llave en Mano | C88: Santiago | D88: Investigación en Proceso | G88: Claudio Fredes (Jefe de Tecnologías) | H88: cfredes@ecopreneur.cl | I88: (56) 2 2334 6422 | K88: 96.778.160-6 | L88: Ventas: GRANDE 3 (600.000 - 1.000.000 UF) | Empleados: 44 | M88: Tier 1 - OPORTUNIDAD ACTIVA (VIP)
A89: Ecoriles S.A. | B89: Tratamiento de Residuos Industriales, Tratamiento de Riles | C89: Santiago | G89: Gerente de TI / CIO (Director de Tecnología) | I89: (56) 2 2569 2238 | K89: 96.945.210-3 | L89: Ventas: GRANDE 4 (Mas de 1.000.000 UF) | Empleados: 324 | M89: Tier 1 - VIP (Alta Venta + DM)
A90: Ecse Construcciones y Servicios Ltda. | B90: Revestimientos Antiácidos | C90: Talcahuano | G90: Gerente de TI / CIO (Director de Tecnología) | I90: (56) 41 256 1000 | K90: 86.680.300-5 | L90: Ventas: GRANDE 3 (600.000 - 1.000.000 UF) | Empleados: 447 | M90: Tier 1 - VIP (Alta Venta + DM)
A91: Efco de Chile S.A. | B91: Alzaprimas, Encofrados | C91: Santiago | G91: Gerente de TI / CIO (Director de Tecnología) | I91: (56) 2 2591 4000 | K91: 96.842.020-8 | L91: Ventas: GRANDE 3 (600.000 - 1.000.000 UF) | Empleados: 111 | M91: Tier 1 - VIP (Alta Venta + DM)
A92: Electricidad Guzmán S.A. | B92: Conductores Eléctricos | C92: Santiago | G92: Gerente de TI / CIO (Director de Tecnología) | I92: (56) 2 2387 1100 | K92: 79.748.470-9 | L92: Ventas: GRANDE 3 (600.000 - 1.000.000 UF) | Empleados: 113 | M92: Tier 1 - VIP (Alta Venta + DM)
A93: Electropower | B93: Torres de Iluminación | C93: Santiago | G93: Gerente de TI / CIO (Director de Tecnología) | I93: (56) 9 5404 2333 | K93: 76.257.832-8 | L93: Ventas: GRANDE 3 (600.000 - 1.000.000 UF) | Empleados: 31 | M93: Tier 1 - VIP (Alta Venta + DM)
A94: Electroram Telecomunicaciones Ltda. | B94: Radiocomunicaciones, Telecomunicaciones | C94: Antofagasta | D94: Conectividad Satelital Fleet Space Minería | F94: https://cl.linkedin.com/in/martha-aguilera-alderete-850117121 | G94: Martha Aguilera (Gerente Innovación) | I94: (56) 55 256 1670 | K94: 76025110-0 | L94: Ventas: GRANDE 2 (200.000 - 600.000 UF) | Empleados: 102 | M94: Tier 1 - OPORTUNIDAD ACTIVA (VIP)
A95: Elfle Comercial Dos Ltda. | B95: Artículos Eléctricos, Suministros para Computación | C95: Santiago | D95: Investigación en Proceso | G95: Gabriel Andres Pérez Gonzalez (Encargado TI) | H95: gabriel.perez@elfle.cl | I95: (56) 2 2733 3000 | K95: 76.085.400-K | L95: Ventas: GRANDE 3 (600.000 - 1.000.000 UF) | Empleados: 24 | M95: Tier 1 - OPORTUNIDAD ACTIVA (VIP)
A96: Empresas Perrot | B96: Transporte Terrestre | C96: Santiago | D96: Investigación en Proceso | G96: Mario Ceron (Gerente TI & Digital) | H96: mario.ceron@perrot.cl | I96: (56) 2 2876 2700 | K96: 77.532.910-6 | L96: Ventas: GRANDE 3 (600.000 - 1.000.000 UF) | Empleados: 146 | M96: Tier 1 - OPORTUNIDAD ACTIVA (VIP)
A97: Emsipor Ltda. | B97: Seguridad Industrial y Minera | C97: Antofagasta | G97: Gerente de TI / CIO (Director de Tecnología) | I97: (56) 55 293 0571 | K97: 77.134.000-8 | L97: Ventas: GRANDE 3 (600.000 - 1.000.000 UF) | Empleados: 479 | M97: Tier 1 - VIP (Alta Venta + DM)
A98: Enaex Servicios | B98: Servicios para Tronaduras | C98: Santiago | D98: Transf. Digital OCC & Soluciones IT/OT | F98: https://cl.linkedin.com/in/jcastrogorostiza | G98: Jose Miguel Castro Gorostiza (Gerente Tecnologia) | I98: (56) 2 2837 7600 | K98: 76.041.871-4 | L98: Ventas: GRANDE (Estimado por Empleados) | Empleados: 2168 | M98: Tier 1 - OPORTUNIDAD ACTIVA (VIP)
A99: Energía Llaima SpA | B99: Energías Renovables | C99: Santiago | G99: Gerente de TI / CIO (Director de Tecnología) | I99: (56) 2 2378 7979 | K99: 76.097.069-7 | L99: Ventas: GRANDE 3 (600.000 - 1.000.000 UF) | Empleados: 49 | M99: Tier 1 - VIP (Alta Venta + DM)
A100: Energías Industriales S.A. (EISA) | B100: Arriendo de Calderas Generadoras a Vapor y Agua Caliente, Asesoría Eficiencia Calderas y Equipos Relacionados, Reparación de Calderas | C100: Santiago | D100: Investigación en Proceso | G100: Mario Tapia Sottorff (Gerente de Operaciones) | H100: mtapia@eisa.cl | I100: (56) 2 2440 8300 | K100: 85.145.500-0 | L100: Ventas: GRANDE 3 (600.000 - 1.000.000 UF) | Empleados: 198 | M100: Tier 1 - OPORTUNIDAD ACTIVA (VIP)
...

Sheet BASE_COMPLETA_LIMPIA
A1: Empresa | B1: Rubro | C1: Ciudad | D1: Email General | E1: Teléfono | F1: Contacto Sniper | G1: Email Directo / Área | H1: Sitio Web | I1: RUT | J1: Oportunidad Detectada | K1: Otros Datos | L1: Estado Contacto | M1: Sub-Estado | N1: Fecha Contacto | O1: Notas CRM | P1: Medio de Contacto | Q1: Próximo Seguimiento | R1: Prioridad | S1: Fecha_Email_Enviado
A2: 350renewables | B2: Consultoría Energías Renovables | C2: Santiago | E2: (56) 9 7648 9569 | I2: 76.429.792-K | K2: Ventas: PEQUEÑA 2 (5.000 - 10.000 UF) | Empleados: 2
A3: 3M Chile S.A. | B3: Productos Eléctricos, Productos para Seguridad | C3: Santiago | D3: atencionconsumidor@mmm.com | E3: 600 300 3636 | I3: 93.626.000-4 | K3: Ventas: MEDIANA (Estimado por Empleados) | Empleados: 179
A4: 4E Chile Giz | B4: Energía, Transmisión de Energía | C4: Santiago | D4: contacto@4echile.cl | E4: (56) 2 2306 8600 | K4: Ventas: No en base SII | Empleados: S/I
A5: A. Hartrodt Chile S.A. | B5: Transporte Aéreo, Transporte Marítimo, Transporte Terrestre | C5: Santiago | D5: ah.scl@hartrodt.com | E5: (56) 2 2483 7000 | F5: Hector Calderon (Jefe Informática) | G5: hcalderon@hartrodt.cl | I5: 84.007.300-9 | J5: Investigación en Proceso | K5: Ventas: GRANDE 3 (600.000 - 1.000.000 UF) | Empleados: 34
A6: A. Marshall Moffat Ltda. | B6: Elementos de Protección Personal, Prendas de Protección Ignífuga contra Arco Eléctrico, Ropa para Seguridad | C6: Valparaíso | D6: chile@marshallmoffat.com | E6: (56) 32 279 5401 | I6: 76.007.072-6 | K6: Ventas: GRANDE 1 (100.000 - 200.000 UF) | Empleados: 62
A7: A.J. Broom y Cía. S.A.C. | B7: Agencias Marítimas | C7: Santiago | D7: info@broomgroup.com | E7: (56) 2 2549 8400 | F7: Ricardo Lira (Gerente Operaciones) | I7: 91.256.000-7 | J7: Plataforma Tracking Marítimo Real-Time | K7: Ventas: GRANDE 2 (200.000 - 600.000 UF) | Empleados: 33
A8: A.R. Thompson Group | B8: Control y Sellado de Fluidos | C8: Concepción | D8: ventaschile@artesinc.com | E8: (56) 41 285 3903 | I8: 76.008.785-8 | K8: Ventas: PEQUEÑA 2 (5.000 - 10.000 UF) | Empleados: 7
A9: AB Arriendos S.A. | B9: Arriendo de Equipos para Soldar, Compresores | C9: Santiago | D9: abarriendos@abarriendos.cl | E9: (56) 2 2351 5400 | F9: Roberto Carlos Bailac (Exec. Director) | I9: 96.872.010-4 | J9: Expansión Arriendo Maquinaria Norte | K9: Ventas: GRANDE 2 (200.000 - 600.000 UF) | Empleados: 107
A10: Abastec, Abastecimientos Técnicos Ltda. | B10: Suministros Industriales | C10: Santiago | D10: ventas@abastec.cl | E10: (56) 2 2776 4726 | I10: 77.783.750-8 | K10: Ventas: GRANDE 1 (100.000 - 200.000 UF) | Empleados: 17
A11: Abasterm S.A. | B11: Calderas, Controles de Nivel | C11: Santiago | D11: contactoasa@abasterm.cl | E11: (56) 2 2566 6800 | I11: 99.532.330-3 | K11: Ventas: GRANDE 1 (100.000 - 200.000 UF) | Empleados: 38
A12: Abastibletec | B12: Proveedor Destacado, Proyectos y Mantenimiento Eléctrico MT y AT, Remanufactura y Metrología en Terreno, Soluciones de Energías Renovables, Soluciones de Huella de Agua y Carbono, Soluciones Eléctricas, Soluciones en Sistemas de Gestión de Energía, Soluciones en Sistemas de Gestión de Integridad de Instalaciones Eléctricas, Soluciones Térmicas, Soluciones y Servicios de Eficiencia Energética, Soluciones y Servicios de IA | C12: Santiago | D12: andre.lamagdelaine@abastibletec.cl | H12: http://www.abastible.cl/abastibletec | I12: 77.528.709-8 | K12: Ventas: MEDIANA 2 (50.000 - 100.000 UF) | Empleados: 37
A13: ABB S.A. | B13: Automatización, Energías Renovables | C13: Santiago | D13: contact.center@cl.abb.com | E13: (56) 2 2471 4100 | I13: 92.805.000-9 | K13: Ventas: GRANDE (Estimado por Empleados) | Empleados: 447
A14: ABCDust | B14: Proveedor Destacado, Control de Polvo, Enzimas para Aplicación Industrial y de Caminos, Productos Químicos, Servicios de Modelación Ambiental y Túneles de Viento, Venta de GPS y Equipamiento de Georreferenciación | C14: Santiago | D14: info@abcdust.net | E14: (56) 2 2897 4905 | H14: http://www.abcdust.net | I14: 76.343.796-5 | K14: Ventas: MEDIANA 2 (50.000 - 100.000 UF) | Empleados: 7
A15: Abengoa Chile S.A. | B15: Energía Solar | C15: Santiago | D15: comercialchile@abengoa.com | E15: (56) 2 2461 4900 | I15: 96.521.440-2 | K15: Ventas: GRANDE (Estimado por Empleados) | Empleados: 3965
A16: ABSG Consulting Inc. | B16: Servicios de Ingeniería | C16: Santiago | D16: absqechile@abs-qe.com | E16: (56) 2 2431 5334 | I16: 85.623.600-5 | K16: Ventas: PEQUEÑA 3 (10.000 - 25.000 UF) | Empleados: 9
A17: AC Perforaciones | B17: Servicios de Perforación | C17: Coquimbo | D17: contactar@acperforaciones.cl | E17: (56) 51 256 6580 | I17: 76610230-1 | K17: Ventas: GRANDE 3 (600.000 - 1.000.000 UF) | Empleados: 509
A18: Accenture Chile | B18: Asesorías Comerciales, Consultoría | C18: Santiago | D18: nestor.leal@accenture.com | E18: (56) 2 2337 7121 | I18: 78.809.770-0 | K18: Ventas: GRANDE (Estimado por Empleados) | Empleados: 2234
A19: Acciona Construcción S.A. | B19: Construcción de Obras Civiles, Construcción de Obras de Infraestructura | C19: Santiago | D19: prensa@acciona.com | E19: (56) 2 2751 5100 | I19: 59.069.860-1 | K19: Ventas: GRANDE (Estimado por Empleados) | Empleados: 3829
A20: Acciona Energía Chile SpA | B20: Energías Renovables | C20: Santiago | D20: inversores@acciona.com | E20: (56) 2 2751 5160 | F20: Gerente de TI / CIO (Director de Tecnología) | I20: 76.492.150-K | K20: Ventas: GRANDE 4 (Mas de 1.000.000 UF) | Empleados: 182
A21: Acermet Ltda. | B21: Aceros Inoxidables, Planchas de Cobre | C21: Santiago | D21: ventas.casamatriz@acermet.cl | E21: (56) 2 2584 5200 | I21: 87.717.600-2 | K21: Ventas: GRANDE 3 (600.000 - 1.000.000 UF) | Empleados: 60
A22: Acerorack | B22: Rack Altillo Estructural | C22: Santiago | D22: ventas@acerorack.cl | E22: (56) 9 9320 7002 | F22: Gerente de TI / CIO (Director de Tecnología) | I22: 77.247.510-1 | K22: Ventas: GRANDE 3 (600.000 - 1.000.000 UF) | Empleados: 88
A23: Aceros AZA | B23: Proveedor Destacado, Aceros al Carbono, Aceros Estructurales, Aceros Laminados, Angulos Laminados de Acero, Construcción de Edificios Habitacionales, Construcción de Galpones de Acero, Construcción de Obras Civiles, Construcción de Obras de Infraestructura, Construcción de Obras para Minería Subterránea | C23: Santiago | D23: contacto@aza.cl | E23: (56) 2 2677 9100 | H23: http://www.aza.cl | I23: 92.176.000-0 | K23: Ventas: GRANDE (Estimado por Empleados) | Empleados: 744
A24: Aceros Chilca | B24: Bolas de Acero Forjado para Molienda, Bolas para molienda, Revestimientos para Molinos | C24: Santiago | D24: info@aceroschilca.com | E24: (56) 2 2929 5486 | F24: Eduardo Garcia (Country Manager) | I24: 96.871.960-2 | J24: Modernización Fundición Piezas Mineras | K24: Ventas: GRANDE 2 (200.000 - 600.000 UF) | Empleados: 4
A25: Aceros Titanium Chile Ltda. | B25: Tubos de Acero | C25: Santiago | D25: ventas@acerostitanium.cl | E25: (56) 2 2948 8444 | I25: 76.190.734-4 | K25: Ventas: GRANDE 1 (100.000 - 200.000 UF) | Empleados: 9
A26: Acerostock | B26: Aceros, Aceros Inoxidables, Aluminio en Barras | C26: Santiago | D26: ventas@acerostock.cl | E26: (56) 2 2556 7677 | I26: 78.151.970-7 | K26: Ventas: PEQUEÑA 3 (10.000 - 25.000 UF) | Empleados: 3
A27: Acetogen Gas Chile S.A. | B27: Artículos para Seguridad | C27: Santiago | D27: televentas@acetogen.cl | E27: (56) 2 2583 2780 | F27: Hugo Inzulza Daneri (Gerente General) | G27: hinzulza@acetogen.cl | I27: 93.333.000-1 | J27: Investigación en Proceso | K27: Ventas: GRANDE 3 (600.000 - 1.000.000 UF) | Empleados: 57
A28: Achilles | B28: Proveedor Destacado, Auditorías Virtuales y Presenciales de la Cadena de Suministro, Cadenas de Suministro | C28: Santiago | D28: maria.peralta@achilles.com | E28: (56) 2 2585 9600 | H28: http://www.achilles.com/es/ | I28: 76.110.170-6 | K28: Ventas: MEDIANA 2 (50.000 - 100.000 UF) | Empleados: 33
A29: Acma S.A. | B29: Cadenas de Acero | C29: Santiago | D29: fduran@acma.cl | E29: (56) 2 2350 6600 | I29: 92.190.000-7 | K29: Ventas: MEDIANA (Estimado por Empleados) | Empleados: 177
A30: Acoplados Metalcar | B30: Carros de Arrastre, Transpaletas | C30: Santiago | D30: carlosd@metalcar.cl | E30: (56) 2 2238 2429 | I30: 77.611.294-1 | K30: Ventas: MEDIANA 2 (50.000 - 100.000 UF) | Empleados: 5
A31: Acquatron Comercial Ltda. | B31: Bombas Dosificadoras | C31: Santiago | D31: acquatron@tie.cl | E31: (56) 2 2264 0339 | I31: 76.682.610-5 | K31: Ventas: MEDIANA 1 (25.000 - 50.000 UF) | Empleados: 3
A32: Actilux | B32: Torres Poligonal y Tubulares | C32: Santiago | D32: info@actilux.cl | E32: (56) 2 2748 6213 | I32: 76.552.367-2 | K32: Ventas: PEQUEÑA 3 (10.000 - 25.000 UF) | Empleados: 0
A33: Acting Chile Ltda. | B33: Equipos Eléctricos, Proyectos para Iluminación | C33: Santiago | D33: contacto@acting.cl | E33: (56) 2 2736 0281 | I33: 78.177.130-9 | K33: Ventas: GRANDE 1 (100.000 - 200.000 UF) | Empleados: 23
A34: Adecco | B34: Consultora de Gestión de Recursos Humanos, Selección y Reclutamiento de Ejecutivos y Personal | C34: Santiago | D34: consultas@adecco.com | E34: (56) 2 2560 7200 | I34: 96.820.170-0 | K34: Ventas: GRANDE (Estimado por Empleados) | Empleados: 9532
A35: Adelanta Asesorías y Servicios | B35: Consultoría en Gestión de Abastecimiento | C35: Santiago | D35: adelanta@adelanta.cl | E35: (56) 9 9883 1453 | I35: 76.425.905-K | K35: Ventas: MEDIANA 2 (50.000 - 100.000 UF) | Empleados: 37
A36: Adizol | B36: Aditivos para Combustibles, Resinas para Pinturas | C36: Santiago | D36: adizol@adizol.com | E36: (56) 2 2657 2670 | I36: 76.183.070-8 | K36: Ventas: GRANDE 1 (100.000 - 200.000 UF) | Empleados: 8
A37: Adler Steel Chile | B37: Aceros Antiabrasivos, Barras de Aceros Especiales | C37: Santiago | D37: ventas@adler.cl | E37: (56) 2 2420 5555 | F37: Sabin Capetillo (Jefe Informática) | G37: scapetillo@adlersteel.cl | I37: 92.844.000-1 | J37: Aceros Especiales Minería (Procesos Críticos) | K37: Ventas: GRANDE 3 (600.000 - 1.000.000 UF) | Empleados: 17
A38: Adtrium | B38: Proveedor Destacado | C38: Santiago | D38: contacto@adtrium.cl | H38: http://www.adtrium.cl | I38: 76.261.771-4 | K38: Ventas: MEDIANA 1 (25.000 - 50.000 UF) | Empleados: 13
A39: Aenor Chile S.A. | B39: Certificación de Calidad, Servicios de Inspección Técnica | C39: Santiago | D39: masanhueza@aenor.com | E39: (56) 2 2499 9200 | I39: 96.968.660-0 | K39: Ventas: GRANDE 1 (100.000 - 200.000 UF) | Empleados: 25
A40: Aerisfogo - Aquaterra | B40: Asesoría Técnica en Indumentaria y Seguridad Industrial, Diseño y Fabricación de Ropa Técnica, Ropa de Trabajo, Comercialización de Equipos de Protección Personal (EPP), Ropa Ignífuga, Ropa Técnica para Minería, Soluciones Integrales en Vestuario Laboral, Vestuario de Alto Desempeño para Faenas, Vestuario de Seguridad Industrial | C40: Santiago | D40: aquaterra@aquaterra.cl | E40: (56) 2 2602 1020 | H40: http://www.aerisfogo.com | I40: 76.073.000-9 | K40: Ventas: MEDIANA 2 (50.000 - 100.000 UF) | Empleados: 13
A41: Aerocardal Ltda. | B41: Transporte Aéreo en Helicóptero, Vuelos Ambulancia | C41: Santiago | D41: aerocardal@aerocardal.com | E41: (56) 2 2377 7400 | F41: Javier Arellano (Jefe IT) | G41: jarellano@aerocardal.com | I41: 78.035.640-5 | J41: Mantenimiento Digital Embraer (Servicio Autorizado) | K41: Ventas: GRANDE 3 (600.000 - 1.000.000 UF) | Empleados: 98
A42: AeroRescate Ambulancias Aéreas | B42: Transporte Aéreo, Transporte Aéreo en Helicóptero | C42: Santiago | D42: ventas@dap.cl | E42: (56) 2 3202 6890 | F42: David Acevedo Olguín (Director Corporativo) | G42: dacevedo@dap.cl | I42: 99.543.620-5 | J42: Investigación en Proceso | K42: Ventas: GRANDE 4 (Mas de 1.000.000 UF) | Empleados: 35
A43: Aerotop | B43: Aerofotogrametría, Cartografía | C43: Santiago | D43: aerotop@aerotop.cl | E43: (56) 2 2235 7728 | I43: 86.264.200-7 | K43: Ventas: MEDIANA 1 (25.000 - 50.000 UF) | Empleados: 14
A44: AES Andes | B44: Transmisión de Energía Eléctrica | C44: Santiago | D44: asuntos.corporativos@aes.com | E44: (56) 2 3333 8300 | I44: 94.272.000-9 | K44: Ventas: GRANDE (Estimado por Empleados) | Empleados: 940
A45: Agecomet S.A. | B45: Accesorios para Perforación, Aceros para Perforación, Elementos para Perforación | C45: Santiago | D45: perfo@agecomet.com | E45: (56) 2 2739 0190 | I45: 96.508.740-0 | K45: Ventas: GRANDE 2 (200.000 - 600.000 UF) | Empleados: 38
A46: Aggreko | B46: Almacenamiento de Energía, Plantas de Energía Híbrida | C46: Santiago | D46: AggrekoPowerSolutionsLAM@aggreko.com | E46: (56) 2 2 4723 902 | I46: 76.625.330-K | K46: Ventas: GRANDE 3 (600.000 - 1.000.000 UF) | Empleados: 114
A47: Aginox Comercial Ltda. | B47: Aceros Inoxidables | C47: Santiago | D47: j.ventas@aginox.cl | E47: (56) 2 2862 5600 | I47: 78.240.410-5 | K47: Ventas: MEDIANA 2 (50.000 - 100.000 UF) | Empleados: 12
A48: Agnov Solutions | B48: Telecomunicaciones, Redes, Cableado, Cyberseguridad | C48: Santiago | E48: (56) 2 2836 0200 | I48: 76.092.344-3 | K48: Ventas: GRANDE 1 (100.000 - 200.000 UF) | Empleados: 23
A49: Agroandina - Induagro | B49: Cúpulas y Encapsulados para Correas Transportadoras | C49: Santiago | D49: ventas@induagro.cl | E49: (56) 2 2551 9834 | I49: 89.243.500-6 | K49: Ventas: MEDIANA 1 (25.000 - 50.000 UF) | Empleados: 24
A50: AGT-Group, American Gate Trading S.A. | B50: Sistemas para Molienda | C50: Santiago | D50: info@agt.cl | E50: (56) 2 3252 9353 | I50: 78.090.920-k | K50: Ventas: PEQUEÑA 3 (10.000 - 25.000 UF) | Empleados: 4
A51: Aguamarket y Cía. Ltda. | B51: Proyectos para Agua Potable | C51: Santiago | D51: gerencia@aguamarket.com | E51: (56) 9 6844 2657 | I51: 77.595.290-3 | K51: Ventas: MEDIANA 1 (25.000 - 50.000 UF) | Empleados: 8
A52: Aguapur Vapor SpA | B52: Calderas, Válvulas para Control, Válvulas para Procesos | C52: Santiago | D52: ventas@aguapurvapor.cl | E52: (56) 2 2727 5237 | I52: 76.312.365-0 | K52: Ventas: MEDIANA 2 (50.000 - 100.000 UF) | Empleados: 11
A53: Aguaquim SpA | B53: Bombas para Transferencia de Corrosivos y Dosificación de Químicos, Equipos para Control en Tratamiento de Aguas y Riles | C53: Santiago | D53: contacto@aguaquim.cl | E53: (56) 9 8409 2768 | I53: 96.938.510-4 | K53: Ventas: MEDIANA 2 (50.000 - 100.000 UF) | Empleados: 13
A54: Aguas Sipra | B54: Plantas para Tratamiento de Agua | C54: Santiago | D54: contacto@aguassipra.cl | E54: (56) 9 4041 2683 | I54: 77.561.380-7 | K54: Ventas: PEQUEÑA 1 (2.400 - 5.000 UF) | Empleados: 1
A55: Aguas y Riles S.A. | B55: Plantas para Tratamiento de Agua, Proyectos para Desalinización, Sistemas para Tratamiento de Aguas Industriales y Residuales | C55: Santiago | D55: info@almarwaterservices.com | E55: (56) 2 6465 5395 | I55: 96.954.690-6 | K55: Ventas: GRANDE (Estimado por Empleados) | Empleados: 836
A56: Aguasin SpA | B56: Sistemas para Purificación de Agua, Tratamiento de Aguas | C56: Santiago | D56: aguasin@aguasin.com | E56: (56) 2 2270 9500 | F56: Richard Correa (Gerente Admin (IT Resp)) | G56: rcorrea@aguasin.com | I56: 76.377.649-2 | J56: Mantención Telemetría Plantas PW | K56: Ventas: GRANDE 4 (Mas de 1.000.000 UF) | Empleados: 174
A57: Agunsa, Agencias Universales S.A. | B57: Agencias de Carga, Almacenamiento de Carga, Transporte de Minerales | C57: Santiago | D57: mineria@agunsa.com | E57: (56) 2 2460 2700 | F57: Carlos Ramírez (CTO Corporativo) | I57: 96.566.940-K | J57: Estrategia Global Innovación Digital | K57: Ventas: GRANDE (Estimado por Empleados) | Empleados: 796
A58: AHK-Asmin | B58: Consultoría en Metalurgia | C58: Santiago | D58: propuestas@ahkgroup.com | E58: (56) 2 2949 3600 | I58: 77.927.460-8 | K58: Ventas: GRANDE 3 (600.000 - 1.000.000 UF) | Empleados: 297
A59: AIA, Asociación de Industriales de Antofagasta | B59: Proveedor Destacado, Asociación de Industriales de Antofagasta, Plataforma para Selección y Monitores de Proveedores de la Minería, Preselección de Proveedores | C59: Antofagasta | D59: secretaria@aia.cl | E59: (56) 55 245 4300 | H59: http://www.aia.cl | I59: 70.372.500-7 | K59: Ventas: GRANDE 3 (600.000 - 1.000.000 UF) | Empleados: 83
A60: Aiko Logic SpA | B60: Tecnología para Optimizar el Rendimiento de Combustible en Vehículos Mineros | C60: Santiago | D60: contacto@aikologic.com | E60: (56) 2 2951 5102 | I60: 76.201.941-8 | K60: Ventas: MEDIANA 2 (50.000 - 100.000 UF) | Empleados: 45
A61: Aimtec Ltda. | B61: Cables de Acero, Equipos para Izaje | C61: Santiago | D61: info@aimtec.cl | E61: (56) 2 2635 4048 | I61: 78.103.880-6 | K61: Ventas: GRANDE 1 (100.000 - 200.000 UF) | Empleados: 40
A62: Air Products /Indura S.A. | B62: Plantas para Gases Industriales, Soldaduras Especiales | C62: Santiago | D62: infocl@airproducts.com | E62: (56) 2 2530 3000 | I62: 76.150.343-K | K62: Ventas: GRANDE (Estimado por Empleados) | Empleados: 662
A63: Airolite S.A. | B63: Aire Acondicionado, Climatización, Proyectos de Ventilación | C63: Santiago | D63: central@airolite.cl | E63: (56) 2 2345 5200 | I63: 92.681.000-6 | K63: Ventas: GRANDE 3 (600.000 - 1.000.000 UF) | Empleados: 66
A64: Aislantes Nacionales SpA | B64: Adhesivos para Cerámicas | C64: Santiago | D64: infono@bekron.cl | E64: (56) 2 2540 3000 | I64: 76.350.871-4 | K64: Ventas: MEDIANA (Estimado por Empleados) | Empleados: 190
A65: Aislantes y Envases Ltda. | B65: Aislantes Térmicos | C65: Santiago | D65: contacto@aislantesyenvases.cl | E65: (56) 2255 24290 | I65: 77.546.260-4 | K65: Ventas: PEQUEÑA 3 (10.000 - 25.000 UF) | Empleados: 7
A66: Aislapol S.A. | B66: Aislantes Térmicos, Envases de Plástico | C66: Santiago | D66: aislapol@styropek.com | E66: (56) 2 2670 0105 | F66: Gerente de TI / CIO (Director de Tecnología) | I66: 76.412.645-9 | K66: Ventas: GRANDE 4 (Mas de 1.000.000 UF) | Empleados: 358
A67: Aitec S.A. | B67: Aspersores para Lixiviación | C67: Santiago | D67: ventas@aitec.cl | E67: (56) 2 2204 9000 | I67: 96.931.710-9 | K67: Ventas: GRANDE 2 (200.000 - 600.000 UF) | Empleados: 46
A68: Ajax Ltda. | B68: Seguridad Industrial y Minera | C68: Santiago | D68: contacto@ajax.cl | E68: (56) 2 2244 1141 | I68: 85.141.600-5 | K68: Ventas: GRANDE 1 (100.000 - 200.000 UF) | Empleados: 17
A69: AKD International (Chile) S.A. | B69: Servicios de Perforación | C69: Antofagasta | D69: global@akdint.com | E69: (56) 55 2423245 | I69: 76206541-K | K69: Ventas: GRANDE 3 (600.000 - 1.000.000 UF) | Empleados: 394
A70: Alen Walung S.A. | B70: Energías Renovables | C70: Santiago | D70: contacto@alenwalung.cl | E70: (56) 2 2223 2346 | I70: 76.148.678-0 | K70: Ventas: PEQUEÑA 1 (2.400 - 5.000 UF) | Empleados: 0
A71: Alessandri & Cía. Ltda. | B71: Asesorías Jurídicas en Minería, Servicios Legales | C71: Santiago | D71: alessandri@alessandri.cl | E71: (56) 2 2787 6000 | F71: Francisco Javier Fernández M. (Subgerente Ops) | I71: 79.784.430-6 | J71: Implementación LegalTech & Ciberseguridad | K71: Ventas: GRANDE 3 (600.000 - 1.000.000 UF) | Empleados: 101
A72: Alfa Laval SpA | B72: Decantadores Centrífugos | C72: Santiago | D72: alfa.consulta@alfalaval.com | E72: (56) 2 2353 0300 | I72: 92.231.000-9 | K72: Ventas: GRANDE 3 (600.000 - 1.000.000 UF) | Empleados: 40
A73: Alfa People Chile SpA | B73: Diseño de Sistemas ERP | C73: Santiago | D73: info.cl@alfapeople.com | E73: (56) 2 2751 9000 | F73: Carlos Amaro (CEO) | I73: 76.360.577-9 | J73: Proyectos Microsoft Dynamics 365 Cloud | K73: Ventas: GRANDE 3 (600.000 - 1.000.000 UF) | Empleados: 121
A74: Alfred H. Knight Int. Ltda. | B74: Análisis Químico, Control de Calidad | C74: Santiago | D74: enquiries@ahkgroup.com | E74: (56) 2 2252 0900 | I74: 78.182.740-1 | K74: Ventas: GRANDE 3 (600.000 - 1.000.000 UF) | Empleados: 663
A75: Alicopsa S.A. | B75: Servicios de Gastronomía | C75: Santiago | D75: alicopsa@alicopsa.cl | E75: (56) 2 2873 0400 | I75: 79.690.660-K | K75: Ventas: GRANDE (Estimado por Empleados) | Empleados: 2827
A76: Aliservice | B76: Alimentación Industrial | C76: Santiago | D76: comercial@aliservice.cl | E76: (56) 2 2913 5500 | F76: Luis Alberto Santana (Gerente Adm y Finanzas) | I76: 76437608-0 | J76: Digitalización Cadena Suministro Alimentación | K76: Ventas: GRANDE 3 (600.000 - 1.000.000 UF) | Empleados: 1372
A77: All In Marketing SpA | B77: Proveedor Destacado, Producción de Mobiliario Publicitario y Stands Modulares, Proyectos Especiales para Eventos y Retail, Soportes Gráficos | C77: Rancagua | D77: nicolas@allin.cl | E77: (56) 9 9499 5487 | H77: http://www.allin.cl | I77: 76.348.327-4 | K77: Ventas: MEDIANA 2 (50.000 - 100.000 UF) | Empleados: 16
A78: All Machine Ltda. | B78: Reparación de Maquinaria para la Minería | C78: Iquique | D78: allmachine@allmachine.cl | E78: (56) 57 224 6000 | I78: 77.496.440-1 | K78: Ventas: MEDIANA 2 (50.000 - 100.000 UF) | Empleados: 74
A79: Allen Ltda. | B79: Aceros Inoxidables | C79: Santiago | D79: pedrohs@allen.cl | E79: (56) 2 2555 3918 | I79: 78.769.930-8 | K79: Ventas: MEDIANA 2 (50.000 - 100.000 UF) | Empleados: 16
A80: Allied Electronics | B80: Artículos Eléctricos, Artículos Electrónicos, Automatización | C80: Santiago | D80: ventas@rschile.cl | E80: (56) 2 2822 8000 | I80: 78.912.510-4 | K80: Ventas: GRANDE 1 (100.000 - 200.000 UF) | Empleados: 18
A81: Almarza S.A. | B81: Tubos de Acero | C81: Santiago | D81: ventas@almarza.cl | E81: (56) 2 2950 9000 | I81: 76.375.265-8 | K81: Ventas: GRANDE 2 (200.000 - 600.000 UF) | Empleados: 73
A82: ALS Inspection Chile | B82: Certificación de Equipos para Izaje | C82: Viña del Mar | D82: humberto.arroyo@alsglobal.com | E82: (56) 32 254 5500 | I82: 76.416.643-4 | K82: Ventas: GRANDE 2 (200.000 - 600.000 UF) | Empleados: 302
A83: Altamira Consultores Ltda. | B83: Salud Preventiva | C83: Copiapó | D83: ventas@altamiraltda.cl | E83: (56) 52 224 4593 | I83: 76536526-0 | K83: Ventas: MICRO 2 (200 - 600 UF) | Empleados: 0
A84: Altapro | B84: Artículos de Protección para Altas Temperaturas, Artículos para Protección Personal | C84: Santiago | D84: ventas@altapro.cl | E84: (56) 2 2753 3688 | I84: 76.201.139-5 | K84: Ventas: MEDIANA 2 (50.000 - 100.000 UF) | Empleados: 8
A85: Altec SpA | B85: Adhesivos y Selladores | C85: Santiago | D85: contacto@altecspa.cl | E85: (56) 2 3323 6483 | I85: 76.917.785-K | K85: Ventas: GRANDE 2 (200.000 - 600.000 UF) | Empleados: 19
A86: Alteza Solutions | B86: Barreras y Protecciones Industriales, Polímeros para Reparación y Empalme de Correas Transportadoras | C86: Santiago | D86: info@altezasolutions.com | E86: (56) 2 2897 7727 | I86: 77.060.747-7 | K86: Ventas: PEQUEÑA 2 (5.000 - 10.000 UF) | Empleados: 1
A87: Altitec Chile Ltda. | B87: Artículos para Protección Personal | C87: Santiago | D87: contacto@altitecchile.cl | E87: (56) 2 2887 0113 | I87: 76.312.131-3 | K87: Ventas: MEDIANA 2 (50.000 - 100.000 UF) | Empleados: 22
A88: Alvenius Chilena Ltda. | B88: Tubos de Acero | C88: Santiago | D88: info@alveniuschilena.cl | E88: (56) 2 2482 6018 | I88: 86.077.400-3 | K88: Ventas: GRANDE 2 (200.000 - 600.000 UF) | Empleados: 40
A89: Alvinter Chile | B89: Proveedor Destacado, Camiones y Remolques de Terminal, Torres de Iluminación, Venta de Repuestos, Partes y Piezas | C89: Antofagasta | D89: leonardo@alvinter.com | E89: (56) 9 3924 1689 | H89: http://www.chile.alvinter.com | I89: 77.773.701-1 | K89: Ventas: MICRO 1 (0.01 - 200 UF) | Empleados: 0
A90: Alxar Minería | B90: Cátodos, Concentrado de Cobre | C90: Santiago | D90: contacto@alxar.cl | E90: (56) 2 2461 7180 | I90: 76.320.907-5 | K90: Ventas: GRANDE 3 (600.000 - 1.000.000 UF) | Empleados: 18
A91: Alzatec | B91: Alzaprimas, Andamios, Andamios Multidireccionales | C91: Santiago | D91: contacto@alzatec.com | E91: (56) 2 2706 0910 | I91: 99.522.430-5 | K91: Ventas: GRANDE 2 (200.000 - 600.000 UF) | Empleados: 27
A92: Ambipar Environment | B92: Arriendo de Equipos Sanitarios Portátiles y Tratamientos de Aguas y Riles | C92: Santiago | D92: contacto@ambipar.cl | E92: 600 3200 400 | I92: 96.824.110-9 | K92: Ventas: GRANDE (Estimado por Empleados) | Empleados: 829
A93: Ambitec S.A. | B93: Ventilación Ambiental | C93: Santiago | D93: contacto@ambitec.cl | E93: (56) 2 2298 3592 | I93: 96.913.370-9 | K93: Ventas: MEDIANA 1 (25.000 - 50.000 UF) | Empleados: 11
A94: Amca Systems SpA | B94: Equipos de Control de Polvos y Gases, Servicios de Ingeniería en Ventilación Industrial | C94: Santiago | D94: sales@amcasys.com | E94: (56) 2 3340 0855 | I94: 76711945-3 | K94: Ventas: MEDIANA 2 (50.000 - 100.000 UF) | Empleados: 10
A95: Ameco South America | B95: Proveedor Destacado, Arriendo de Equipos y Maquinaria, Certificación de Operadores, Servicios de Izaje y Levante, Servicios de Movimiento de Material, Servicios de Soporte Operacional | C95: Santiago | D95: contacto@amecosa.com | E95: (56) 2 2444 3700 | H95: http://www.amecosa.com | I95: 96.862.140-8 | K95: Ventas: GRANDE (Estimado por Empleados) | Empleados: 2852
A96: American Parts | B96: Actividades de Apoyo para la Explotación de Minas y Canteras, Venta de Partes, Piezas y Accesorios para Vehículos Automotores | C96: Antofagasta | D96: info@americanparts.cl | E96: (56) 9 4220 1935 | F96: Patricio Herrera (Jefe de Sistemas) | G96: p.herrera@americanparts.cl | H96: http://www.americanparts.cl | I96: 76.790.684-6 | J96: Canal E-commerce B2B (Expansión Digital) | K96: Ventas: GRANDE 3 (600.000 - 1.000.000 UF) | Empleados: 38
A97: American Screw Chile SpA | B97: Artículos para Fijación y Sujeción | C97: Santiago | D97: ventas@amscrew.cl | E97: (56) 2 2440 7000 | I97: 91.410.000-3 | K97: Ventas: GRANDE (Estimado por Empleados) | Empleados: 393
A98: American Shoe S.A. | B98: Calzado para Seguridad | C98: Santiago | E98: (56) 2 2422 9500 | I98: 96.847.060-4 | K98: Ventas: MICRO 2 (200 - 600 UF) | Empleados: 0
A99: Aminpro | B99: Análisis de Datos Mineralógicos | C99: Santiago | D99: info@aminpro.com | E99: (56) 2 2958 2471 | I99: 76.068.167-9 | K99: Ventas: GRANDE 2 (200.000 - 600.000 UF) | Empleados: 100
A100: Ampersand | B100: Tuberías HDPE | C100: Santiago | D100: ventas@ampersandchile.cl | E100: (56) 2 2458 5124 | I100: 76350515-4 | K100: Ventas: MICRO 1 (0.01 - 200 UF) | Empleados: 0
...

Sheet OUTREACH_LINKEDIN
A1: Empresa | B1: Contacto | C1: Cargo | D1: Categoría | E1: LinkedIn Personal | F1: Mensaje LinkedIn — copiar y pegar | G1: Estado
A2: A. Hartrodt Chile S.A. | B2: Hector | C2: Jefe Informática | D2: Logística | E2: https://cl.linkedin.com/in/hector-calderon-gonzalez-3439a358 | F2: Hola Hector, vi que A. Hartrodt Chile S.A. opera en logística y transporte. En OpenCORE desarrollamos plataformas que conectan tracking, WMS y ERP en tiempo real. ¿Tienen desafíos con visibilidad de carga o trazabilidad operativa?
A3: A.J. Broom y Cía. S.A.C. | B3: Ricardo | C3: Gerente Operaciones | D3: Logística | E3: nan | F3: Hola Ricardo, vi que A.J. Broom y Cía. S.A.C. opera en logística y transporte. En OpenCORE desarrollamos plataformas que conectan tracking, WMS y ERP en tiempo real. ¿Tienen desafíos con visibilidad de carga o trazabilidad operativa?
A4: AB Arriendos S.A. | B4: Roberto | C4: Exec. Director | D4: Arriendo Maq. | E4: nan | F4: Hola Roberto, sé que AB Arriendos S.A. trabaja con arriendo de equipos industriales. OpenCORE desarrolla software de control de flota y mantenimiento predictivo. ¿Tienen algún desafío en la gestión de equipos o disponibilidad de activos?
A5: Aceros Chilca | B5: Eduardo | C5: Country Manager | D5: Minería | E5: nan | F5: Hola Eduardo, trabajo con empresas del sector minero en digitalización de operaciones. En OpenCORE construimos sistemas de gestión de activos y trazabilidad para faenas. ¿Están evaluando mejorar el control de procesos críticos en Aceros Chilca?
A6: Acetogen Gas Chile S.A. | B6: Hugo | C6: Gerente General | D6: Seguridad/EPP | E6: nan | F6: Hola Hugo, trabajo con distribuidores de EPP e industria química. En OpenCORE desarrollamos plataformas B2B para inventario, pedidos y trazabilidad. ¿Acetogen Gas Chile S.A. tiene desafíos en gestión de inventario o canal de ventas B2B?
A7: Adler Steel Chile | B7: Sabin | C7: Jefe Informática | D7: Minería | E7: https://cl.linkedin.com/in/sabin-capetillo-83376711a | F7: Hola Sabin, trabajo con empresas del sector minero en digitalización de operaciones. En OpenCORE construimos sistemas de gestión de activos y trazabilidad para faenas. ¿Están evaluando mejorar el control de procesos críticos en Adler Steel Chile?
A8: AeroRescate Ambulancias Aéreas | B8: David | C8: Director Corporativo | D8: Logística | E8: https://cl.linkedin.com/in/david-acevedo-olgu%C3%ADn-01586b56 | F8: Hola David, vi que AeroRescate Ambulancias Aéreas opera en logística y transporte. En OpenCORE desarrollamos plataformas que conectan tracking, WMS y ERP en tiempo real. ¿Tienen desafíos con visibilidad de carga o trazabilidad operativa?
A9: Aerocardal Ltda. | B9: Javier | C9: Jefe IT | D9: Logística | E9: https://cl.linkedin.com/in/javier-arellano-28087313 | F9: Hola Javier, vi que Aerocardal Ltda. opera en logística y transporte. En OpenCORE desarrollamos plataformas que conectan tracking, WMS y ERP en tiempo real. ¿Tienen desafíos con visibilidad de carga o trazabilidad operativa?
A10: Aguasin SpA | B10: Richard | C10: Gerente Admin (IT Resp | D10: Industrial | E10: https://cl.linkedin.com/in/richard-correa-escudero-6820b484 | F10: Hola Richard, en OpenCORE desarrollamos software para operaciones industriales: gestión de activos, trazabilidad y control operacional a medida. ¿Hay algún proceso en Aguasin SpA donde estén evaluando digitalizar o mejorar eficiencia?
A11: Agunsa, Agencias Universales S.A. | B11: Carlos | C11: CTO Corporativo | D11: Logística | E11: https://cl.linkedin.com/in/carlos-ram%C3%ADrez-c%C3%A1rdenas-tecnolog%C3%ADa | F11: Hola Carlos, vi que Agunsa, Agencias Universales S.A. opera en logística y transporte. En OpenCORE desarrollamos plataformas que conectan tracking, WMS y ERP en tiempo real. ¿Tienen desafíos con visibilidad de carga o trazabilidad operativa?
A12: Alessandri & Cía. Ltda. | B12: Francisco | C12: Subgerente Ops | D12: Minería | E12: https://cl.linkedin.com/in/francisco-fern%C3%A1ndez-mancilla | F12: Hola Francisco, trabajo con empresas del sector minero en digitalización de operaciones. En OpenCORE construimos sistemas de gestión de activos y trazabilidad para faenas. ¿Están evaluando mejorar el control de procesos críticos en Alessandri & Cía. Ltda.?
A13: Alfa People Chile SpA | B13: Carlos | C13: CEO | D13: Industrial | E13: nan | F13: Hola Carlos, en OpenCORE desarrollamos software para operaciones industriales: gestión de activos, trazabilidad y control operacional a medida. ¿Hay algún proceso en Alfa People Chile SpA donde estén evaluando digitalizar o mejorar eficiencia?
... A233: Zitrón Chile SpA | B233: Nelson | C233: Subgerente TI | D233: Industrial | E233: nan | F233: Hola Nelson, en OpenCORE desarrollamos software para operaciones industriales: gestión de activos, trazabilidad y control operacional a medida. ¿Hay algún proceso en Zitrón Chile SpA donde estén evaluando digitalizar o mejorar eficiencia?

Sheet NOTAS_DASHBOARD
A1: Fecha | B1: Comentario
A2: 17/03/2026 | B2: Probando la funcionalidad
